[
  {
    "raceId": "2023-12-06-HV-1",
    "date": "2023-12-06",
    "racecourse": "HV",
    "raceNo": 1,
    "raceIndex": 223,
    "raceClass": 5,
    "distance": 1200,
    "ratingBand": "40-0",
    "surface": "TURF",
    "course": "TURF - \"A\" Course",
    "going": "GOOD",
    "runners": [
      {
        "placing": 1,
        "horseNo": 1,
        "horseId": "HK_2022_H224",
        "brandNo": "H224",
        "horseName": "DIAMOND FLARE",
        "jockey": "L Ferraris",
        "trainer": "M Newnham",
        "actualWeight": 135,
        "declaredHorseWeight": 1278,
        "draw": 3,
        "lbw": 0,
        "runningPosition": [
          1,
          1,
          1
        ],
        "finishSeconds": 70.77,
        "winOdds": 7.5
      },
      {
        "placing": 2,
        "horseNo": 3,
        "horseId": "HK_2018_C476",
        "brandNo": "C476",
        "horseName": "HERCULES",
        "jockey": "K Teetan",
        "trainer": "C H Yip",
        "actualWeight": 133,
        "declaredHorseWeight": 1050,
        "draw": 1,
        "lbw": 0.05,
        "runningPosition": [
          6,
          4,
          2
        ],
        "finishSeconds": 70.83,
        "winOdds": 8.1
      },
      {
        "placing": 3,
        "horseNo": 9,
        "horseId": "HK_2021_G423",
        "brandNo": "G423",
        "horseName": "EASY TWO",
        "jockey": "C L Chau",
        "trainer": "K H Ting",
        "actualWeight": 121,
        "declaredHorseWeight": 1053,
        "draw": 4,
        "lbw": 0.5,
        "runningPosition": [
          9,
          9,
          3
        ],
        "finishSeconds": 70.87,
        "winOdds": 33
      },
      {
        "placing": 4,
        "horseNo": 7,
        "horseId": "HK_2021_G352",
        "brandNo": "G352",
        "horseName": "MODEST GENTLEMAN",
        "jockey": "L Hewitson",
        "trainer": "K W Lui",
        "actualWeight": 129,
        "declaredHorseWeight": 1054,
        "draw": 5,
        "lbw": 1,
        "runningPosition": [
          8,
          8,
          4
        ],
        "finishSeconds": 70.95,
        "winOdds": 7.2
      },
      {
        "placing": 5,
        "horseNo": 5,
        "horseId": "HK_2022_H068",
        "brandNo": "H068",
        "horseName": "CRYSTAL POWERFUL",
        "jockey": "B Avdulla",
        "trainer": "W K Mo",
        "actualWeight": 131,
        "declaredHorseWeight": 1135,
        "draw": 2,
        "lbw": 1.75,
        "runningPosition": [
          7,
          5,
          5
        ],
        "finishSeconds": 71.06,
        "winOdds": 8
      },
      {
        "placing": 6,
        "horseNo": 4,
        "horseId": "HK_2020_E495",
        "brandNo": "E495",
        "horseName": "VALHALLA",
        "jockey": "C Y Ho",
        "trainer": "C Fownes",
        "actualWeight": 133,
        "declaredHorseWeight": 1169,
        "draw": 6,
        "lbw": 3,
        "runningPosition": [
          4,
          2,
          6
        ],
        "finishSeconds": 71.27,
        "winOdds": 3.4
      },
      {
        "placing": 7,
        "horseNo": 2,
        "horseId": "HK_2020_E149",
        "brandNo": "E149",
        "horseName": "H Z TOURBILLON",
        "jockey": "T Marquand",
        "trainer": "T P Yung",
        "actualWeight": 135,
        "declaredHorseWeight": 1040,
        "draw": 12,
        "lbw": 3.75,
        "runningPosition": [
          11,
          10,
          7
        ],
        "finishSeconds": 71.36,
        "winOdds": 24
      },
      {
        "placing": 8,
        "horseNo": 6,
        "horseId": "HK_2020_E208",
        "brandNo": "E208",
        "horseName": "GOODMANSHIP",
        "jockey": "J McDonald",
        "trainer": "D J Whyte",
        "actualWeight": 129,
        "declaredHorseWeight": 1169,
        "draw": 11,
        "lbw": 4,
        "runningPosition": [
          3,
          3,
          8
        ],
        "finishSeconds": 71.41,
        "winOdds": 14
      },
      {
        "placing": 9,
        "horseNo": 12,
        "horseId": "HK_2020_E138",
        "brandNo": "E138",
        "horseName": "NOIR RIDER",
        "jockey": "H Doyle",
        "trainer": "C W Chang",
        "actualWeight": 118,
        "declaredHorseWeight": 1186,
        "draw": 8,
        "lbw": 4,
        "runningPosition": [
          12,
          12,
          9
        ],
        "finishSeconds": 71.43,
        "winOdds": 14
      },
      {
        "placing": 10,
        "horseNo": 11,
        "horseId": "HK_2021_G043",
        "brandNo": "G043",
        "horseName": "SUPER HORNET",
        "jockey": "A Atzeni",
        "trainer": "J Richards",
        "actualWeight": 119,
        "declaredHorseWeight": 1091,
        "draw": 10,
        "lbw": 5.25,
        "runningPosition": [
          10,
          11,
          10
        ],
        "finishSeconds": 71.63,
        "winOdds": 50
      },
      {
        "placing": 11,
        "horseNo": 10,
        "horseId": "HK_2020_E156",
        "brandNo": "E156",
        "horseName": "NOBLE BOYZ",
        "jockey": "A Badel",
        "trainer": "K L Man",
        "actualWeight": 120,
        "declaredHorseWeight": 1188,
        "draw": 7,
        "lbw": 26.25,
        "runningPosition": [
          5,
          7,
          11
        ],
        "finishSeconds": 74.96000000000001,
        "winOdds": 10
      },
      {
        "placing": 12,
        "horseNo": 8,
        "horseId": "HK_2020_E211",
        "brandNo": "E211",
        "horseName": "DRAGON KINGDOM",
        "jockey": "K C Leung",
        "trainer": "Y S Tsui",
        "actualWeight": 125,
        "declaredHorseWeight": 1162,
        "draw": 9,
        "lbw": 36,
        "runningPosition": [
          2,
          6,
          12
        ],
        "finishSeconds": 76.53,
        "winOdds": 13
      }
    ],
    "dividends": {
      "win": [
        {
          "pool": "WIN",
          "combination": [
            1
          ],
          "dividendPer10": 75.5
        }
      ],
      "place": [
        {
          "pool": "PLACE",
          "combination": [
            1
          ],
          "dividendPer10": 24.5
        },
        {
          "pool": "PLACE",
          "combination": [
            3
          ],
          "dividendPer10": 22
        },
        {
          "pool": "PLACE",
          "combination": [
            9
          ],
          "dividendPer10": 77.5
        }
      ],
      "quinella": [
        {
          "pool": "QUINELLA",
          "combination": [
            1,
            3
          ],
          "dividendPer10": 326.5
        }
      ],
      "quinellaPlace": [
        {
          "pool": "QUINELLA PLACE",
          "combination": [
            1,
            3
          ],
          "dividendPer10": 110
        },
        {
          "pool": "QUINELLA PLACE",
          "combination": [
            1,
            9
          ],
          "dividendPer10": 357.5
        },
        {
          "pool": "QUINELLA PLACE",
          "combination": [
            3,
            9
          ],
          "dividendPer10": 341
        }
      ],
      "forecast": [
        {
          "pool": "FORECAST",
          "combination": [
            1,
            3
          ],
          "dividendPer10": 575
        }
      ],
      "tierce": [
        {
          "pool": "TIERCE",
          "combination": [
            1,
            3,
            9
          ],
          "dividendPer10": 12676
        }
      ],
      "trio": [
        {
          "pool": "TRIO",
          "combination": [
            1,
            3,
            9
          ],
          "dividendPer10": 3150
        }
      ],
      "first4": [
        {
          "pool": "FIRST 4",
          "combination": [
            1,
            3,
            7,
            9
          ],
          "dividendPer10": 3790
        }
      ],
      "quartet": [
        {
          "pool": "QUARTET",
          "combination": [
            1,
            3,
            9,
            7
          ],
          "dividendPer10": 90265
        }
      ]
    },
    "source": "https://racing.hkjc.com/en-us/local/information/localresults?racedate=2023%2F12%2F06&Racecourse=HV&RaceNo=1"
  },
  {
    "raceId": "2023-12-06-HV-2",
    "date": "2023-12-06",
    "racecourse": "HV",
    "raceNo": 2,
    "raceIndex": 224,
    "raceClass": 5,
    "distance": 1650,
    "ratingBand": "40-0",
    "surface": "TURF",
    "course": "TURF - \"A\" Course",
    "going": "GOOD",
    "runners": [
      {
        "placing": 1,
        "horseNo": 4,
        "horseId": "HK_2021_G470",
        "brandNo": "G470",
        "horseName": "NICE BIRDIE",
        "jockey": "C L Chau",
        "trainer": "C S Shum",
        "actualWeight": 126,
        "declaredHorseWeight": 1185,
        "draw": 11,
        "lbw": 0,
        "runningPosition": [
          7,
          1,
          2,
          1
        ],
        "finishSeconds": 103.33,
        "winOdds": 30
      },
      {
        "placing": 2,
        "horseNo": 8,
        "horseId": "HK_2021_G129",
        "brandNo": "G129",
        "horseName": "MEDIC ELITE",
        "jockey": "H Doyle",
        "trainer": "P C Ng",
        "actualWeight": 123,
        "declaredHorseWeight": 1105,
        "draw": 8,
        "lbw": 0.2,
        "runningPosition": [
          2,
          2,
          1,
          2
        ],
        "finishSeconds": 103.36,
        "winOdds": 7.6
      },
      {
        "placing": 3,
        "horseNo": 10,
        "horseId": "HK_2020_E311",
        "brandNo": "E311",
        "horseName": "HANG'S CHOICE",
        "jockey": "K Teetan",
        "trainer": "W Y So",
        "actualWeight": 119,
        "declaredHorseWeight": 1079,
        "draw": 7,
        "lbw": 0.5,
        "runningPosition": [
          9,
          5,
          5,
          3
        ],
        "finishSeconds": 103.43,
        "winOdds": 6.4
      },
      {
        "placing": 4,
        "horseNo": 5,
        "horseId": "HK_2021_H004",
        "brandNo": "H004",
        "horseName": "ONE HEART ONE",
        "jockey": "L Hewitson",
        "trainer": "D A Hayes",
        "actualWeight": 128,
        "declaredHorseWeight": 1155,
        "draw": 10,
        "lbw": 2,
        "runningPosition": [
          10,
          12,
          10,
          4
        ],
        "finishSeconds": 103.64,
        "winOdds": 13
      },
      {
        "placing": 5,
        "horseNo": 6,
        "horseId": "HK_2022_H030",
        "brandNo": "H030",
        "horseName": "BROTHER PEARL",
        "jockey": "L Ferraris",
        "trainer": "C H Yip",
        "actualWeight": 127,
        "declaredHorseWeight": 1032,
        "draw": 1,
        "lbw": 2.25,
        "runningPosition": [
          5,
          9,
          9,
          5
        ],
        "finishSeconds": 103.71000000000001,
        "winOdds": 11
      },
      {
        "placing": 6,
        "horseNo": 3,
        "horseId": "HK_2020_E069",
        "brandNo": "E069",
        "horseName": "HAPPY JAI JAI",
        "jockey": "Z Purton",
        "trainer": "T P Yung",
        "actualWeight": 131,
        "declaredHorseWeight": 1099,
        "draw": 4,
        "lbw": 2.75,
        "runningPosition": [
          4,
          6,
          6,
          6
        ],
        "finishSeconds": 103.77000000000001,
        "winOdds": 3.8
      },
      {
        "placing": 7,
        "horseNo": 7,
        "horseId": "HK_2020_E489",
        "brandNo": "E489",
        "horseName": "LOYAL AMBITION",
        "jockey": "J McDonald",
        "trainer": "C Fownes",
        "actualWeight": 125,
        "declaredHorseWeight": 1029,
        "draw": 5,
        "lbw": 3,
        "runningPosition": [
          6,
          8,
          8,
          7
        ],
        "finishSeconds": 103.78999999999999,
        "winOdds": 7.7
      },
      {
        "placing": 8,
        "horseNo": 11,
        "horseId": "HK_2019_D491",
        "brandNo": "D491",
        "horseName": "MISTER ARM",
        "jockey": "H T Mo",
        "trainer": "Y S Tsui",
        "actualWeight": 117,
        "declaredHorseWeight": 1035,
        "draw": 3,
        "lbw": 3,
        "runningPosition": [
          1,
          3,
          4,
          8
        ],
        "finishSeconds": 103.81,
        "winOdds": 34
      },
      {
        "placing": 9,
        "horseNo": 1,
        "horseId": "HK_2021_G437",
        "brandNo": "G437",
        "horseName": "CHARMANDER",
        "jockey": "C Y Ho",
        "trainer": "J Richards",
        "actualWeight": 135,
        "declaredHorseWeight": 1155,
        "draw": 9,
        "lbw": 3.25,
        "runningPosition": [
          8,
          11,
          11,
          9
        ],
        "finishSeconds": 103.85,
        "winOdds": 9.1
      },
      {
        "placing": 10,
        "horseNo": 9,
        "horseId": "HK_2021_G250",
        "brandNo": "G250",
        "horseName": "DOUBLE SHOW",
        "jockey": "T Marquand",
        "trainer": "D J Whyte",
        "actualWeight": 122,
        "declaredHorseWeight": 1213,
        "draw": 2,
        "lbw": 4.25,
        "runningPosition": [
          3,
          7,
          7,
          10
        ],
        "finishSeconds": 104,
        "winOdds": 9.6
      },
      {
        "placing": 11,
        "horseNo": 2,
        "horseId": "HK_2020_E487",
        "brandNo": "E487",
        "horseName": "CIRCUIT ELITE",
        "jockey": "B Avdulla",
        "trainer": "A S Cruz",
        "actualWeight": 135,
        "declaredHorseWeight": 1246,
        "draw": 12,
        "lbw": 7,
        "runningPosition": [
          11,
          4,
          3,
          11
        ],
        "finishSeconds": 104.47,
        "winOdds": 29
      },
      {
        "placing": 12,
        "horseNo": 12,
        "horseId": "HK_2020_E328",
        "brandNo": "E328",
        "horseName": "COMPULSORY",
        "jockey": "A Atzeni",
        "trainer": "C W Chang",
        "actualWeight": 116,
        "declaredHorseWeight": 1122,
        "draw": 6,
        "lbw": 11.5,
        "runningPosition": [
          12,
          10,
          12,
          12
        ],
        "finishSeconds": 105.19,
        "winOdds": 15
      }
    ],
    "dividends": {
      "win": [
        {
          "pool": "WIN",
          "combination": [
            4
          ],
          "dividendPer10": 307.5
        }
      ],
      "place": [
        {
          "pool": "PLACE",
          "combination": [
            4
          ],
          "dividendPer10": 81
        },
        {
          "pool": "PLACE",
          "combination": [
            8
          ],
          "dividendPer10": 28
        },
        {
          "pool": "PLACE",
          "combination": [
            10
          ],
          "dividendPer10": 22.5
        }
      ],
      "quinella": [
        {
          "pool": "QUINELLA",
          "combination": [
            4,
            8
          ],
          "dividendPer10": 1330
        }
      ],
      "quinellaPlace": [
        {
          "pool": "QUINELLA PLACE",
          "combination": [
            4,
            8
          ],
          "dividendPer10": 374
        },
        {
          "pool": "QUINELLA PLACE",
          "combination": [
            4,
            10
          ],
          "dividendPer10": 305
        },
        {
          "pool": "QUINELLA PLACE",
          "combination": [
            8,
            10
          ],
          "dividendPer10": 109
        }
      ],
      "forecast": [
        {
          "pool": "FORECAST",
          "combination": [
            4,
            8
          ],
          "dividendPer10": 3413
        }
      ],
      "tierce": [
        {
          "pool": "TIERCE",
          "combination": [
            4,
            8,
            10
          ],
          "dividendPer10": 21422
        }
      ],
      "trio": [
        {
          "pool": "TRIO",
          "combination": [
            4,
            8,
            10
          ],
          "dividendPer10": 2465
        }
      ],
      "first4": [
        {
          "pool": "FIRST 4",
          "combination": [
            4,
            5,
            8,
            10
          ],
          "dividendPer10": 4785
        }
      ],
      "quartet": [
        {
          "pool": "QUARTET",
          "combination": [
            4,
            8,
            10,
            5
          ],
          "dividendPer10": 159228
        }
      ]
    },
    "source": "https://racing.hkjc.com/en-us/local/information/localresults?racedate=2023%2F12%2F06&Racecourse=HV&RaceNo=2"
  },
  {
    "raceId": "2023-12-06-HV-3",
    "date": "2023-12-06",
    "racecourse": "HV",
    "raceNo": 3,
    "raceIndex": 225,
    "raceClass": 4,
    "distance": 1650,
    "ratingBand": "60-40",
    "surface": "TURF",
    "course": "TURF - \"A\" Course",
    "going": "GOOD",
    "runners": [
      {
        "placing": 1,
        "horseNo": 10,
        "horseId": "HK_2022_H346",
        "brandNo": "H346",
        "horseName": "SIMPLY MAVERICK",
        "jockey": "A Atzeni",
        "trainer": "P F Yiu",
        "actualWeight": 122,
        "declaredHorseWeight": 1206,
        "draw": 5,
        "lbw": 0,
        "runningPosition": [
          2,
          2,
          2,
          1
        ],
        "finishSeconds": 100.75999999999999,
        "winOdds": 4.8
      },
      {
        "placing": 2,
        "horseNo": 8,
        "horseId": "HK_2017_B085",
        "brandNo": "B085",
        "horseName": "FEARLESS FIRE",
        "jockey": "K Teetan",
        "trainer": "D A Hayes",
        "actualWeight": 124,
        "declaredHorseWeight": 1159,
        "draw": 2,
        "lbw": 4.75,
        "runningPosition": [
          3,
          5,
          5,
          2
        ],
        "finishSeconds": 101.50999999999999,
        "winOdds": 4.2
      },
      {
        "placing": 3,
        "horseNo": 7,
        "horseId": "HK_2021_G150",
        "brandNo": "G150",
        "horseName": "TURIN WARRIOR",
        "jockey": "Z Purton",
        "trainer": "K L Man",
        "actualWeight": 125,
        "declaredHorseWeight": 1086,
        "draw": 12,
        "lbw": 5.5,
        "runningPosition": [
          9,
          9,
          9,
          3
        ],
        "finishSeconds": 101.65,
        "winOdds": 4.7
      },
      {
        "placing": 4,
        "horseNo": 9,
        "horseId": "HK_2019_D419",
        "brandNo": "D419",
        "horseName": "LEGION OF MERIT",
        "jockey": "B Avdulla",
        "trainer": "W Y So",
        "actualWeight": 123,
        "declaredHorseWeight": 1274,
        "draw": 6,
        "lbw": 6.5,
        "runningPosition": [
          10,
          10,
          10,
          4
        ],
        "finishSeconds": 101.78999999999999,
        "winOdds": 17
      },
      {
        "placing": 5,
        "horseNo": 4,
        "horseId": "HK_2021_G151",
        "brandNo": "G151",
        "horseName": "LOOKING COOL",
        "jockey": "M Barzalona",
        "trainer": "F C Lor",
        "actualWeight": 129,
        "declaredHorseWeight": 1131,
        "draw": 9,
        "lbw": 7.5,
        "runningPosition": [
          11,
          11,
          12,
          5
        ],
        "finishSeconds": 101.95,
        "winOdds": 17
      },
      {
        "placing": 6,
        "horseNo": 12,
        "horseId": "HK_2019_D164",
        "brandNo": "D164",
        "horseName": "DRAGON PRIDE",
        "jockey": "C L Chau",
        "trainer": "T P Yung",
        "actualWeight": 120,
        "declaredHorseWeight": 1106,
        "draw": 8,
        "lbw": 7.5,
        "runningPosition": [
          12,
          12,
          11,
          6
        ],
        "finishSeconds": 101.97,
        "winOdds": 28
      },
      {
        "placing": 7,
        "horseNo": 6,
        "horseId": "HK_2022_H214",
        "brandNo": "H214",
        "horseName": "CHATEAU",
        "jockey": "A Badel",
        "trainer": "J Size",
        "actualWeight": 125,
        "declaredHorseWeight": 1061,
        "draw": 11,
        "lbw": 8,
        "runningPosition": [
          5,
          3,
          3,
          7
        ],
        "finishSeconds": 102.03,
        "winOdds": 19
      },
      {
        "placing": 8,
        "horseNo": 5,
        "horseId": "HK_2021_G364",
        "brandNo": "G364",
        "horseName": "SUPER BABY",
        "jockey": "L Ferraris",
        "trainer": "M Newnham",
        "actualWeight": 126,
        "declaredHorseWeight": 1184,
        "draw": 4,
        "lbw": 9,
        "runningPosition": [
          1,
          1,
          1,
          8
        ],
        "finishSeconds": 102.18,
        "winOdds": 24
      },
      {
        "placing": 9,
        "horseNo": 2,
        "horseId": "HK_2020_E351",
        "brandNo": "E351",
        "horseName": "ROYAL PRIDE",
        "jockey": "J McDonald",
        "trainer": "C Fownes",
        "actualWeight": 133,
        "declaredHorseWeight": 1077,
        "draw": 7,
        "lbw": 9.75,
        "runningPosition": [
          6,
          8,
          8,
          9
        ],
        "finishSeconds": 102.3,
        "winOdds": 6.1
      },
      {
        "placing": 10,
        "horseNo": 11,
        "horseId": "HK_2019_D513",
        "brandNo": "D513",
        "horseName": "AMAZING BOY",
        "jockey": "T Marquand",
        "trainer": "C W Chang",
        "actualWeight": 121,
        "declaredHorseWeight": 1090,
        "draw": 1,
        "lbw": 10.5,
        "runningPosition": [
          4,
          4,
          4,
          10
        ],
        "finishSeconds": 102.43,
        "winOdds": 9.8
      },
      {
        "placing": 11,
        "horseNo": 1,
        "horseId": "HK_2021_G112",
        "brandNo": "G112",
        "horseName": "LUCKY GOLD",
        "jockey": "L Hewitson",
        "trainer": "K W Lui",
        "actualWeight": 135,
        "declaredHorseWeight": 1198,
        "draw": 10,
        "lbw": 10.5,
        "runningPosition": [
          8,
          6,
          6,
          11
        ],
        "finishSeconds": 102.44,
        "winOdds": 25
      },
      {
        "placing": 12,
        "horseNo": 3,
        "horseId": "HK_2022_H268",
        "brandNo": "H268",
        "horseName": "MERCHANT PRINCE",
        "jockey": "K C Leung",
        "trainer": "J Richards",
        "actualWeight": 132,
        "declaredHorseWeight": 1180,
        "draw": 3,
        "lbw": 12.5,
        "runningPosition": [
          7,
          7,
          7,
          12
        ],
        "finishSeconds": 102.75,
        "winOdds": 81
      }
    ],
    "dividends": {
      "win": [
        {
          "pool": "WIN",
          "combination": [
            10
          ],
          "dividendPer10": 48.5
        }
      ],
      "place": [
        {
          "pool": "PLACE",
          "combination": [
            10
          ],
          "dividendPer10": 24.5
        },
        {
          "pool": "PLACE",
          "combination": [
            8
          ],
          "dividendPer10": 17.5
        },
        {
          "pool": "PLACE",
          "combination": [
            7
          ],
          "dividendPer10": 16
        }
      ],
      "quinella": [
        {
          "pool": "QUINELLA",
          "combination": [
            8,
            10
          ],
          "dividendPer10": 129
        }
      ],
      "quinellaPlace": [
        {
          "pool": "QUINELLA PLACE",
          "combination": [
            8,
            10
          ],
          "dividendPer10": 50.5
        },
        {
          "pool": "QUINELLA PLACE",
          "combination": [
            7,
            10
          ],
          "dividendPer10": 54.5
        },
        {
          "pool": "QUINELLA PLACE",
          "combination": [
            7,
            8
          ],
          "dividendPer10": 39
        }
      ],
      "forecast": [
        {
          "pool": "FORECAST",
          "combination": [
            10,
            8
          ],
          "dividendPer10": 285
        }
      ],
      "tierce": [
        {
          "pool": "TIERCE",
          "combination": [
            10,
            8,
            7
          ],
          "dividendPer10": 1126
        }
      ],
      "trio": [
        {
          "pool": "TRIO",
          "combination": [
            7,
            8,
            10
          ],
          "dividendPer10": 196
        }
      ],
      "first4": [
        {
          "pool": "FIRST 4",
          "combination": [
            7,
            8,
            9,
            10
          ],
          "dividendPer10": 679
        }
      ],
      "quartet": [
        {
          "pool": "QUARTET",
          "combination": [
            10,
            8,
            7,
            9
          ],
          "dividendPer10": 12663
        }
      ]
    },
    "source": "https://racing.hkjc.com/en-us/local/information/localresults?racedate=2023%2F12%2F06&Racecourse=HV&RaceNo=3"
  },
  {
    "raceId": "2023-12-06-HV-4",
    "date": "2023-12-06",
    "racecourse": "HV",
    "raceNo": 4,
    "raceIndex": 226,
    "raceClass": 4,
    "distance": 1000,
    "ratingBand": "60-40",
    "surface": "TURF",
    "course": "TURF - \"A\" Course",
    "going": "GOOD",
    "runners": [
      {
        "placing": 1,
        "horseNo": 11,
        "horseId": "HK_2018_C361",
        "brandNo": "C361",
        "horseName": "OVERSUBSCRIBED",
        "jockey": "R King",
        "trainer": "D J Hall",
        "actualWeight": 119,
        "declaredHorseWeight": 1184,
        "draw": 5,
        "lbw": 0,
        "runningPosition": [
          4,
          4,
          1
        ],
        "finishSeconds": 57.62,
        "winOdds": 10
      },
      {
        "placing": 2,
        "horseNo": 3,
        "horseId": "HK_2020_E175",
        "brandNo": "E175",
        "horseName": "HARMONY FIRE",
        "jockey": "L Hewitson",
        "trainer": "D J Whyte",
        "actualWeight": 133,
        "declaredHorseWeight": 1110,
        "draw": 12,
        "lbw": 0.75,
        "runningPosition": [
          3,
          2,
          2
        ],
        "finishSeconds": 57.75,
        "winOdds": 21
      },
      {
        "placing": 3,
        "horseNo": 9,
        "horseId": "HK_2021_G201",
        "brandNo": "G201",
        "horseName": "DIAMOND SOARS",
        "jockey": "C Y Ho",
        "trainer": "P F Yiu",
        "actualWeight": 124,
        "declaredHorseWeight": 1210,
        "draw": 4,
        "lbw": 1.25,
        "runningPosition": [
          2,
          3,
          3
        ],
        "finishSeconds": 57.81,
        "winOdds": 7.6
      },
      {
        "placing": 4,
        "horseNo": 12,
        "horseId": "HK_2021_G456",
        "brandNo": "G456",
        "horseName": "SUPER FAST DRAGON",
        "jockey": "Y Kawada",
        "trainer": "J Richards",
        "actualWeight": 118,
        "declaredHorseWeight": 1179,
        "draw": 8,
        "lbw": 1.25,
        "runningPosition": [
          12,
          12,
          4
        ],
        "finishSeconds": 57.83,
        "winOdds": 6.5
      },
      {
        "placing": 5,
        "horseNo": 6,
        "horseId": "HK_2020_E386",
        "brandNo": "E386",
        "horseName": "SAVVY DELIGHT",
        "jockey": "Z Purton",
        "trainer": "J Size",
        "actualWeight": 130,
        "declaredHorseWeight": 1211,
        "draw": 1,
        "lbw": 1.5,
        "runningPosition": [
          6,
          5,
          5
        ],
        "finishSeconds": 57.87,
        "winOdds": 7.9
      },
      {
        "placing": 6,
        "horseNo": 2,
        "horseId": "HK_2019_D350",
        "brandNo": "D350",
        "horseName": "SUPER COMMANDER",
        "jockey": "K Teetan",
        "trainer": "P C Ng",
        "actualWeight": 134,
        "declaredHorseWeight": 1085,
        "draw": 7,
        "lbw": 2.5,
        "runningPosition": [
          1,
          1,
          6
        ],
        "finishSeconds": 58.04,
        "winOdds": 6.8
      },
      {
        "placing": 7,
        "horseNo": 4,
        "horseId": "HK_2022_H147",
        "brandNo": "H147",
        "horseName": "GALVANIC",
        "jockey": "T Marquand",
        "trainer": "C Fownes",
        "actualWeight": 131,
        "declaredHorseWeight": 1090,
        "draw": 3,
        "lbw": 2.75,
        "runningPosition": [
          5,
          7,
          7
        ],
        "finishSeconds": 58.07,
        "winOdds": 4.9
      },
      {
        "placing": 8,
        "horseNo": 5,
        "horseId": "HK_2021_G051",
        "brandNo": "G051",
        "horseName": "GORGEOUS VITALITY",
        "jockey": "B Murzabayev",
        "trainer": "F C Lor",
        "actualWeight": 131,
        "declaredHorseWeight": 1109,
        "draw": 2,
        "lbw": 3.5,
        "runningPosition": [
          8,
          8,
          8
        ],
        "finishSeconds": 58.19,
        "winOdds": 8.3
      },
      {
        "placing": 9,
        "horseNo": 7,
        "horseId": "HK_2020_E359",
        "brandNo": "E359",
        "horseName": "G ONE EXCELLENT",
        "jockey": "M Barzalona",
        "trainer": "C S Shum",
        "actualWeight": 127,
        "declaredHorseWeight": 1227,
        "draw": 9,
        "lbw": 6.5,
        "runningPosition": [
          9,
          10,
          9
        ],
        "finishSeconds": 58.65,
        "winOdds": 49
      },
      {
        "placing": 10,
        "horseNo": 8,
        "horseId": "HK_2023_J067",
        "brandNo": "J067",
        "horseName": "RED MAVERICK",
        "jockey": "R Moore",
        "trainer": "Y S Tsui",
        "actualWeight": 127,
        "declaredHorseWeight": 1269,
        "draw": 11,
        "lbw": 6.5,
        "runningPosition": [
          11,
          11,
          10
        ],
        "finishSeconds": 58.67,
        "winOdds": 85
      },
      {
        "placing": 11,
        "horseNo": 10,
        "horseId": "HK_2019_D474",
        "brandNo": "D474",
        "horseName": "CIRCUIT SEVEN",
        "jockey": "H Doyle",
        "trainer": "A S Cruz",
        "actualWeight": 121,
        "declaredHorseWeight": 1145,
        "draw": 10,
        "lbw": 8,
        "runningPosition": [
          10,
          9,
          11
        ],
        "finishSeconds": 58.9,
        "winOdds": 13
      },
      {
        "placing": 12,
        "horseNo": 1,
        "horseId": "HK_2022_H359",
        "brandNo": "H359",
        "horseName": "AMAZING ACE",
        "jockey": "J McDonald",
        "trainer": "P C Ng",
        "actualWeight": 134,
        "declaredHorseWeight": 1238,
        "draw": 6,
        "lbw": 10,
        "runningPosition": [
          7,
          6,
          12
        ],
        "finishSeconds": 59.22,
        "winOdds": 11
      }
    ],
    "dividends": {
      "win": [
        {
          "pool": "WIN",
          "combination": [
            11
          ],
          "dividendPer10": 105.5
        }
      ],
      "place": [
        {
          "pool": "PLACE",
          "combination": [
            11
          ],
          "dividendPer10": 23
        },
        {
          "pool": "PLACE",
          "combination": [
            3
          ],
          "dividendPer10": 68
        },
        {
          "pool": "PLACE",
          "combination": [
            9
          ],
          "dividendPer10": 27.5
        }
      ],
      "quinella": [
        {
          "pool": "QUINELLA",
          "combination": [
            3,
            11
          ],
          "dividendPer10": 1197
        }
      ],
      "quinellaPlace": [
        {
          "pool": "QUINELLA PLACE",
          "combination": [
            3,
            11
          ],
          "dividendPer10": 310.5
        },
        {
          "pool": "QUINELLA PLACE",
          "combination": [
            9,
            11
          ],
          "dividendPer10": 152
        },
        {
          "pool": "QUINELLA PLACE",
          "combination": [
            3,
            9
          ],
          "dividendPer10": 289.5
        }
      ],
      "forecast": [
        {
          "pool": "FORECAST",
          "combination": [
            11,
            3
          ],
          "dividendPer10": 2513
        }
      ],
      "tierce": [
        {
          "pool": "TIERCE",
          "combination": [
            11,
            3,
            9
          ],
          "dividendPer10": 20890
        }
      ],
      "trio": [
        {
          "pool": "TRIO",
          "combination": [
            3,
            9,
            11
          ],
          "dividendPer10": 3211
        }
      ],
      "first4": [
        {
          "pool": "FIRST 4",
          "combination": [
            3,
            9,
            11,
            12
          ],
          "dividendPer10": 4318
        }
      ],
      "quartet": [
        {
          "pool": "QUARTET",
          "combination": [
            11,
            3,
            9,
            12
          ],
          "dividendPer10": 165042
        }
      ]
    },
    "source": "https://racing.hkjc.com/en-us/local/information/localresults?racedate=2023%2F12%2F06&Racecourse=HV&RaceNo=4"
  },
  {
    "raceId": "2023-12-06-HV-5",
    "date": "2023-12-06",
    "racecourse": "HV",
    "raceNo": 5,
    "raceIndex": 227,
    "raceClass": 4,
    "distance": 1650,
    "ratingBand": "60-40",
    "surface": "TURF",
    "course": "TURF - \"A\" Course",
    "going": "GOOD",
    "runners": [
      {
        "placing": 1,
        "horseNo": 4,
        "horseId": "HK_2021_G466",
        "brandNo": "G466",
        "horseName": "M UNICORN",
        "jockey": "R Moore",
        "trainer": "C Fownes",
        "actualWeight": 130,
        "declaredHorseWeight": 1191,
        "draw": 4,
        "lbw": 0,
        "runningPosition": [
          7,
          6,
          7,
          1
        ],
        "finishSeconds": 101.32,
        "winOdds": 2.6
      },
      {
        "placing": 2,
        "horseNo": 5,
        "horseId": "HK_2022_H188",
        "brandNo": "H188",
        "horseName": "RED HARE KING",
        "jockey": "L Hewitson",
        "trainer": "A S Cruz",
        "actualWeight": 129,
        "declaredHorseWeight": 1092,
        "draw": 3,
        "lbw": 1,
        "runningPosition": [
          5,
          5,
          4,
          2
        ],
        "finishSeconds": 101.47999999999999,
        "winOdds": 6.3
      },
      {
        "placing": 3,
        "horseNo": 11,
        "horseId": "HK_2021_G125",
        "brandNo": "G125",
        "horseName": "SURE JOYFUL",
        "jockey": "C Y Ho",
        "trainer": "P F Yiu",
        "actualWeight": 119,
        "declaredHorseWeight": 1060,
        "draw": 2,
        "lbw": 1,
        "runningPosition": [
          6,
          7,
          6,
          3
        ],
        "finishSeconds": 101.49000000000001,
        "winOdds": 3.6
      },
      {
        "placing": 4,
        "horseNo": 10,
        "horseId": "HK_2021_G304",
        "brandNo": "G304",
        "horseName": "SUPERB MOVE",
        "jockey": "Y Kawada",
        "trainer": "C H Yip",
        "actualWeight": 119,
        "declaredHorseWeight": 1122,
        "draw": 7,
        "lbw": 2.5,
        "runningPosition": [
          8,
          8,
          8,
          4
        ],
        "finishSeconds": 101.72999999999999,
        "winOdds": 31
      },
      {
        "placing": 5,
        "horseNo": 9,
        "horseId": "HK_2021_G098",
        "brandNo": "G098",
        "horseName": "BEAUTY MISSION",
        "jockey": "B Murzabayev",
        "trainer": "F C Lor",
        "actualWeight": 123,
        "declaredHorseWeight": 1036,
        "draw": 12,
        "lbw": 2.75,
        "runningPosition": [
          11,
          11,
          11,
          5
        ],
        "finishSeconds": 101.77000000000001,
        "winOdds": 50
      },
      {
        "placing": 6,
        "horseNo": 3,
        "horseId": "HK_2020_E397",
        "brandNo": "E397",
        "horseName": "SNOWALOT",
        "jockey": "K Teetan",
        "trainer": "D A Hayes",
        "actualWeight": 132,
        "declaredHorseWeight": 1100,
        "draw": 8,
        "lbw": 3.25,
        "runningPosition": [
          12,
          12,
          12,
          6
        ],
        "finishSeconds": 101.83,
        "winOdds": 11
      },
      {
        "placing": 7,
        "horseNo": 1,
        "horseId": "HK_2021_G323",
        "brandNo": "G323",
        "horseName": "WIDE BLUE YONDER",
        "jockey": "J McDonald",
        "trainer": "D A Hayes",
        "actualWeight": 135,
        "declaredHorseWeight": 1118,
        "draw": 11,
        "lbw": 5,
        "runningPosition": [
          2,
          2,
          2,
          7
        ],
        "finishSeconds": 102.13,
        "winOdds": 48
      },
      {
        "placing": 8,
        "horseNo": 2,
        "horseId": "HK_2020_E082",
        "brandNo": "E082",
        "horseName": "DURHAM STAR",
        "jockey": "M Barzalona",
        "trainer": "D J Whyte",
        "actualWeight": 132,
        "declaredHorseWeight": 1178,
        "draw": 5,
        "lbw": 5.75,
        "runningPosition": [
          10,
          10,
          10,
          8
        ],
        "finishSeconds": 102.25,
        "winOdds": 14
      },
      {
        "placing": 9,
        "horseNo": 12,
        "horseId": "HK_2021_G277",
        "brandNo": "G277",
        "horseName": "TO INFINITY",
        "jockey": "R King",
        "trainer": "J Richards",
        "actualWeight": 118,
        "declaredHorseWeight": 1021,
        "draw": 6,
        "lbw": 6.75,
        "runningPosition": [
          9,
          9,
          9,
          9
        ],
        "finishSeconds": 102.42,
        "winOdds": 27
      },
      {
        "placing": 10,
        "horseNo": 6,
        "horseId": "HK_2022_H121",
        "brandNo": "H121",
        "horseName": "TATTENHAM",
        "jockey": "Z Purton",
        "trainer": "P C Ng",
        "actualWeight": 127,
        "declaredHorseWeight": 1106,
        "draw": 10,
        "lbw": 7.5,
        "runningPosition": [
          1,
          1,
          1,
          10
        ],
        "finishSeconds": 102.50999999999999,
        "winOdds": 32
      },
      {
        "placing": 11,
        "horseNo": 7,
        "horseId": "HK_2022_H312",
        "brandNo": "H312",
        "horseName": "CLUB SODA",
        "jockey": "H Doyle",
        "trainer": "J Size",
        "actualWeight": 126,
        "declaredHorseWeight": 1154,
        "draw": 1,
        "lbw": 7.75,
        "runningPosition": [
          3,
          4,
          5,
          11
        ],
        "finishSeconds": 102.53999999999999,
        "winOdds": 15
      },
      {
        "placing": 12,
        "horseNo": 8,
        "horseId": "HK_2021_G020",
        "brandNo": "G020",
        "horseName": "KILLER INSTINCT",
        "jockey": "T Marquand",
        "trainer": "C Fownes",
        "actualWeight": 126,
        "declaredHorseWeight": 1082,
        "draw": 9,
        "lbw": 8.25,
        "runningPosition": [
          4,
          3,
          3,
          12
        ],
        "finishSeconds": 102.63,
        "winOdds": 29
      }
    ],
    "dividends": {
      "win": [
        {
          "pool": "WIN",
          "combination": [
            4
          ],
          "dividendPer10": 26.5
        }
      ],
      "place": [
        {
          "pool": "PLACE",
          "combination": [
            4
          ],
          "dividendPer10": 13.5
        },
        {
          "pool": "PLACE",
          "combination": [
            5
          ],
          "dividendPer10": 17
        },
        {
          "pool": "PLACE",
          "combination": [
            11
          ],
          "dividendPer10": 16
        }
      ],
      "quinella": [
        {
          "pool": "QUINELLA",
          "combination": [
            4,
            5
          ],
          "dividendPer10": 88.5
        }
      ],
      "quinellaPlace": [
        {
          "pool": "QUINELLA PLACE",
          "combination": [
            4,
            5
          ],
          "dividendPer10": 38
        },
        {
          "pool": "QUINELLA PLACE",
          "combination": [
            4,
            11
          ],
          "dividendPer10": 25
        },
        {
          "pool": "QUINELLA PLACE",
          "combination": [
            5,
            11
          ],
          "dividendPer10": 41
        }
      ],
      "forecast": [
        {
          "pool": "FORECAST",
          "combination": [
            4,
            5
          ],
          "dividendPer10": 144
        }
      ],
      "tierce": [
        {
          "pool": "TIERCE",
          "combination": [
            4,
            5,
            11
          ],
          "dividendPer10": 426
        }
      ],
      "trio": [
        {
          "pool": "TRIO",
          "combination": [
            4,
            5,
            11
          ],
          "dividendPer10": 87
        }
      ],
      "first4": [
        {
          "pool": "FIRST 4",
          "combination": [
            4,
            5,
            10,
            11
          ],
          "dividendPer10": 463
        }
      ],
      "quartet": [
        {
          "pool": "QUARTET",
          "combination": [
            4,
            5,
            11,
            10
          ],
          "dividendPer10": 5650
        }
      ]
    },
    "source": "https://racing.hkjc.com/en-us/local/information/localresults?racedate=2023%2F12%2F06&Racecourse=HV&RaceNo=5"
  },
  {
    "raceId": "2023-12-06-HV-6",
    "date": "2023-12-06",
    "racecourse": "HV",
    "raceNo": 6,
    "raceIndex": 228,
    "raceClass": 4,
    "distance": 1200,
    "ratingBand": "60-40",
    "surface": "TURF",
    "course": "TURF - \"A\" Course",
    "going": "GOOD",
    "runners": [
      {
        "placing": 1,
        "horseNo": 6,
        "horseId": "HK_2022_H203",
        "brandNo": "H203",
        "horseName": "HEALTHY HEALTHY",
        "jockey": "Z Purton",
        "trainer": "P C Ng",
        "actualWeight": 131,
        "declaredHorseWeight": 1144,
        "draw": 11,
        "lbw": 0,
        "runningPosition": [
          3,
          2,
          1
        ],
        "finishSeconds": 70.32,
        "winOdds": 5.7
      },
      {
        "placing": 2,
        "horseNo": 9,
        "horseId": "HK_2020_E209",
        "brandNo": "E209",
        "horseName": "ERNEST FEELING",
        "jockey": "A Hamelin",
        "trainer": "J Richards",
        "actualWeight": 123,
        "declaredHorseWeight": 1224,
        "draw": 6,
        "lbw": 0.1,
        "runningPosition": [
          6,
          6,
          2
        ],
        "finishSeconds": 70.34,
        "winOdds": 8.2
      },
      {
        "placing": 3,
        "horseNo": 12,
        "horseId": "HK_2021_G081",
        "brandNo": "G081",
        "horseName": "LYRICAL MOTION",
        "jockey": "A Badel",
        "trainer": "C Fownes",
        "actualWeight": 116,
        "declaredHorseWeight": 1094,
        "draw": 4,
        "lbw": 0.75,
        "runningPosition": [
          5,
          4,
          3
        ],
        "finishSeconds": 70.44,
        "winOdds": 8.2
      },
      {
        "placing": 4,
        "horseNo": 3,
        "horseId": "HK_2020_E236",
        "brandNo": "E236",
        "horseName": "KILINDINI",
        "jockey": "M Barzalona",
        "trainer": "W K Mo",
        "actualWeight": 134,
        "declaredHorseWeight": 1166,
        "draw": 2,
        "lbw": 1,
        "runningPosition": [
          2,
          3,
          4
        ],
        "finishSeconds": 70.48,
        "winOdds": 6.9
      },
      {
        "placing": 5,
        "horseNo": 4,
        "horseId": "HK_2020_E368",
        "brandNo": "E368",
        "horseName": "PARTY WARRIOR",
        "jockey": "C Y Ho",
        "trainer": "K W Lui",
        "actualWeight": 133,
        "declaredHorseWeight": 1044,
        "draw": 1,
        "lbw": 2,
        "runningPosition": [
          7,
          7,
          5
        ],
        "finishSeconds": 70.64,
        "winOdds": 5.9
      },
      {
        "placing": 6,
        "horseNo": 8,
        "horseId": "HK_2021_G388",
        "brandNo": "G388",
        "horseName": "PRINCE CHISWICK",
        "jockey": "T Marquand",
        "trainer": "P F Yiu",
        "actualWeight": 124,
        "declaredHorseWeight": 1179,
        "draw": 7,
        "lbw": 2.25,
        "runningPosition": [
          1,
          1,
          6
        ],
        "finishSeconds": 70.68,
        "winOdds": 9.1
      },
      {
        "placing": 7,
        "horseNo": 5,
        "horseId": "HK_2021_G244",
        "brandNo": "G244",
        "horseName": "HAPPY TRIO",
        "jockey": "L Ferraris",
        "trainer": "D J Whyte",
        "actualWeight": 132,
        "declaredHorseWeight": 1049,
        "draw": 5,
        "lbw": 2.75,
        "runningPosition": [
          4,
          5,
          7
        ],
        "finishSeconds": 70.76,
        "winOdds": 9.6
      },
      {
        "placing": 8,
        "horseNo": 7,
        "horseId": "HK_2022_H242",
        "brandNo": "H242",
        "horseName": "GOLDEN RISE",
        "jockey": "B Avdulla",
        "trainer": "J Size",
        "actualWeight": 127,
        "declaredHorseWeight": 1020,
        "draw": 12,
        "lbw": 3,
        "runningPosition": [
          10,
          10,
          8
        ],
        "finishSeconds": 70.78,
        "winOdds": 14
      },
      {
        "placing": 9,
        "horseNo": 10,
        "horseId": "HK_2018_C531",
        "brandNo": "C531",
        "horseName": "HARMONY N HOME",
        "jockey": "C L Chau",
        "trainer": "C S Shum",
        "actualWeight": 121,
        "declaredHorseWeight": 1071,
        "draw": 8,
        "lbw": 3.25,
        "runningPosition": [
          8,
          8,
          9
        ],
        "finishSeconds": 70.82,
        "winOdds": 29
      },
      {
        "placing": 10,
        "horseNo": 1,
        "horseId": "HK_2019_D487",
        "brandNo": "D487",
        "horseName": "SIGHT HERO",
        "jockey": "J McDonald",
        "trainer": "D A Hayes",
        "actualWeight": 135,
        "declaredHorseWeight": 1312,
        "draw": 10,
        "lbw": 3.25,
        "runningPosition": [
          9,
          9,
          10
        ],
        "finishSeconds": 70.85,
        "winOdds": 22
      },
      {
        "placing": 11,
        "horseNo": 11,
        "horseId": "HK_2022_H189",
        "brandNo": "H189",
        "horseName": "DIAMOND DIAMOND",
        "jockey": "H Doyle",
        "trainer": "T P Yung",
        "actualWeight": 118,
        "declaredHorseWeight": 1201,
        "draw": 3,
        "lbw": 5.25,
        "runningPosition": [
          12,
          11,
          11
        ],
        "finishSeconds": 71.18,
        "winOdds": 13
      },
      {
        "placing": 12,
        "horseNo": 2,
        "horseId": "HK_2018_C460",
        "brandNo": "C460",
        "horseName": "WOOD ON FIRE",
        "jockey": "K Teetan",
        "trainer": "C W Chang",
        "actualWeight": 135,
        "declaredHorseWeight": 1156,
        "draw": 9,
        "lbw": 36,
        "runningPosition": [
          11,
          12,
          12
        ],
        "finishSeconds": 76.06,
        "winOdds": 23
      }
    ],
    "dividends": {
      "win": [
        {
          "pool": "WIN",
          "combination": [
            6
          ],
          "dividendPer10": 57.5
        }
      ],
      "place": [
        {
          "pool": "PLACE",
          "combination": [
            6
          ],
          "dividendPer10": 21
        },
        {
          "pool": "PLACE",
          "combination": [
            9
          ],
          "dividendPer10": 29
        },
        {
          "pool": "PLACE",
          "combination": [
            12
          ],
          "dividendPer10": 28.5
        }
      ],
      "quinella": [
        {
          "pool": "QUINELLA",
          "combination": [
            6,
            9
          ],
          "dividendPer10": 323.5
        }
      ],
      "quinellaPlace": [
        {
          "pool": "QUINELLA PLACE",
          "combination": [
            6,
            9
          ],
          "dividendPer10": 129
        },
        {
          "pool": "QUINELLA PLACE",
          "combination": [
            6,
            12
          ],
          "dividendPer10": 122
        },
        {
          "pool": "QUINELLA PLACE",
          "combination": [
            9,
            12
          ],
          "dividendPer10": 117
        }
      ],
      "forecast": [
        {
          "pool": "FORECAST",
          "combination": [
            6,
            9
          ],
          "dividendPer10": 577
        }
      ],
      "tierce": [
        {
          "pool": "TIERCE",
          "combination": [
            6,
            9,
            12
          ],
          "dividendPer10": 4720
        }
      ],
      "trio": [
        {
          "pool": "TRIO",
          "combination": [
            6,
            9,
            12
          ],
          "dividendPer10": 1022
        }
      ],
      "first4": [
        {
          "pool": "FIRST 4",
          "combination": [
            3,
            6,
            9,
            12
          ],
          "dividendPer10": 843
        }
      ],
      "quartet": [
        {
          "pool": "QUARTET",
          "combination": [
            6,
            9,
            12,
            3
          ],
          "dividendPer10": 19431
        }
      ]
    },
    "source": "https://racing.hkjc.com/en-us/local/information/localresults?racedate=2023%2F12%2F06&Racecourse=HV&RaceNo=6"
  },
  {
    "raceId": "2023-12-06-HV-7",
    "date": "2023-12-06",
    "racecourse": "HV",
    "raceNo": 7,
    "raceIndex": 229,
    "raceClass": 3,
    "distance": 1650,
    "ratingBand": "80-60",
    "surface": "TURF",
    "course": "TURF - \"A\" Course",
    "going": "GOOD",
    "runners": [
      {
        "placing": 1,
        "horseNo": 8,
        "horseId": "HK_2022_H171",
        "brandNo": "H171",
        "horseName": "SILVER SONIC",
        "jockey": "Z Purton",
        "trainer": "K W Lui",
        "actualWeight": 122,
        "declaredHorseWeight": 1095,
        "draw": 7,
        "lbw": 0,
        "runningPosition": [
          4,
          5,
          5,
          1
        ],
        "finishSeconds": 100.69,
        "winOdds": 9.2
      },
      {
        "placing": 2,
        "horseNo": 4,
        "horseId": "HK_2022_H166",
        "brandNo": "H166",
        "horseName": "QUANTUM PATCH",
        "jockey": "M Barzalona",
        "trainer": "P C Ng",
        "actualWeight": 125,
        "declaredHorseWeight": 1128,
        "draw": 9,
        "lbw": 1.5,
        "runningPosition": [
          11,
          11,
          8,
          2
        ],
        "finishSeconds": 100.92,
        "winOdds": 3.2
      },
      {
        "placing": 3,
        "horseNo": 6,
        "horseId": "HK_2020_E355",
        "brandNo": "E355",
        "horseName": "ALL BEAUTY",
        "jockey": "L Hewitson",
        "trainer": "F C Lor",
        "actualWeight": 123,
        "declaredHorseWeight": 1170,
        "draw": 4,
        "lbw": 3.5,
        "runningPosition": [
          6,
          6,
          7,
          3
        ],
        "finishSeconds": 101.24000000000001,
        "winOdds": 10
      },
      {
        "placing": 4,
        "horseNo": 1,
        "horseId": "HK_2020_E192",
        "brandNo": "E192",
        "horseName": "SPLENDID LIVING",
        "jockey": "T Marquand",
        "trainer": "P F Yiu",
        "actualWeight": 134,
        "declaredHorseWeight": 1130,
        "draw": 10,
        "lbw": 3.75,
        "runningPosition": [
          2,
          2,
          2,
          4
        ],
        "finishSeconds": 101.31,
        "winOdds": 18
      },
      {
        "placing": 5,
        "horseNo": 2,
        "horseId": "HK_2021_G452",
        "brandNo": "G452",
        "horseName": "FLAGSHIP WARRIOR",
        "jockey": "J McDonald",
        "trainer": "C Fownes",
        "actualWeight": 131,
        "declaredHorseWeight": 1019,
        "draw": 5,
        "lbw": 4,
        "runningPosition": [
          7,
          7,
          6,
          5
        ],
        "finishSeconds": 101.33,
        "winOdds": 12
      },
      {
        "placing": 6,
        "horseNo": 7,
        "horseId": "HK_2021_G028",
        "brandNo": "G028",
        "horseName": "E LEGEND",
        "jockey": "B Murzabayev",
        "trainer": "K L Man",
        "actualWeight": 122,
        "declaredHorseWeight": 1126,
        "draw": 3,
        "lbw": 4.5,
        "runningPosition": [
          1,
          1,
          1,
          6
        ],
        "finishSeconds": 101.4,
        "winOdds": 11
      },
      {
        "placing": 7,
        "horseNo": 12,
        "horseId": "HK_2020_E472",
        "brandNo": "E472",
        "horseName": "STAR CONTACT",
        "jockey": "R King",
        "trainer": "D A Hayes",
        "actualWeight": 119,
        "declaredHorseWeight": 1204,
        "draw": 8,
        "lbw": 4.5,
        "runningPosition": [
          5,
          4,
          3,
          7
        ],
        "finishSeconds": 101.41,
        "winOdds": 59
      },
      {
        "placing": 8,
        "horseNo": 9,
        "horseId": "HK_2021_G139",
        "brandNo": "G139",
        "horseName": "STORM LEGEND",
        "jockey": "C Y Ho",
        "trainer": "C Fownes",
        "actualWeight": 122,
        "declaredHorseWeight": 1048,
        "draw": 11,
        "lbw": 5.5,
        "runningPosition": [
          10,
          9,
          9,
          8
        ],
        "finishSeconds": 101.58,
        "winOdds": 20
      },
      {
        "placing": 9,
        "horseNo": 5,
        "horseId": "HK_2022_H116",
        "brandNo": "H116",
        "horseName": "IVY LEAGUE",
        "jockey": "R Moore",
        "trainer": "D J Whyte",
        "actualWeight": 124,
        "declaredHorseWeight": 1202,
        "draw": 12,
        "lbw": 6,
        "runningPosition": [
          12,
          12,
          11,
          9
        ],
        "finishSeconds": 101.65,
        "winOdds": 15
      },
      {
        "placing": 10,
        "horseNo": 10,
        "horseId": "HK_2021_G412",
        "brandNo": "G412",
        "horseName": "FLYING MOJITO",
        "jockey": "H Doyle",
        "trainer": "D J Hall",
        "actualWeight": 120,
        "declaredHorseWeight": 1090,
        "draw": 1,
        "lbw": 7.5,
        "runningPosition": [
          9,
          10,
          12,
          10
        ],
        "finishSeconds": 101.89,
        "winOdds": 7.4
      },
      {
        "placing": 11,
        "horseNo": 11,
        "horseId": "HK_2021_G374",
        "brandNo": "G374",
        "horseName": "D STAR",
        "jockey": "Y Kawada",
        "trainer": "A S Cruz",
        "actualWeight": 119,
        "declaredHorseWeight": 1051,
        "draw": 6,
        "lbw": 9.25,
        "runningPosition": [
          8,
          8,
          10,
          11
        ],
        "finishSeconds": 102.18,
        "winOdds": 14
      },
      {
        "placing": 12,
        "horseNo": 3,
        "horseId": "HK_2021_G120",
        "brandNo": "G120",
        "horseName": "SIXTH GENERATION",
        "jockey": "K Teetan",
        "trainer": "J Richards",
        "actualWeight": 126,
        "declaredHorseWeight": 1188,
        "draw": 2,
        "lbw": 9.5,
        "runningPosition": [
          3,
          3,
          4,
          12
        ],
        "finishSeconds": 102.19,
        "winOdds": 7.2
      }
    ],
    "dividends": {
      "win": [
        {
          "pool": "WIN",
          "combination": [
            8
          ],
          "dividendPer10": 92.5
        }
      ],
      "place": [
        {
          "pool": "PLACE",
          "combination": [
            8
          ],
          "dividendPer10": 35.5
        },
        {
          "pool": "PLACE",
          "combination": [
            4
          ],
          "dividendPer10": 15.5
        },
        {
          "pool": "PLACE",
          "combination": [
            6
          ],
          "dividendPer10": 35.5
        }
      ],
      "quinella": [
        {
          "pool": "QUINELLA",
          "combination": [
            4,
            8
          ],
          "dividendPer10": 207.5
        }
      ],
      "quinellaPlace": [
        {
          "pool": "QUINELLA PLACE",
          "combination": [
            4,
            8
          ],
          "dividendPer10": 82.5
        },
        {
          "pool": "QUINELLA PLACE",
          "combination": [
            6,
            8
          ],
          "dividendPer10": 204
        },
        {
          "pool": "QUINELLA PLACE",
          "combination": [
            4,
            6
          ],
          "dividendPer10": 85.5
        }
      ],
      "forecast": [
        {
          "pool": "FORECAST",
          "combination": [
            8,
            4
          ],
          "dividendPer10": 491
        }
      ],
      "tierce": [
        {
          "pool": "TIERCE",
          "combination": [
            8,
            4,
            6
          ],
          "dividendPer10": 5141
        }
      ],
      "trio": [
        {
          "pool": "TRIO",
          "combination": [
            4,
            6,
            8
          ],
          "dividendPer10": 774
        }
      ],
      "first4": [
        {
          "pool": "FIRST 4",
          "combination": [
            1,
            4,
            6,
            8
          ],
          "dividendPer10": 2370
        }
      ],
      "quartet": [
        {
          "pool": "QUARTET",
          "combination": [
            8,
            4,
            6,
            1
          ],
          "dividendPer10": 54393
        }
      ]
    },
    "source": "https://racing.hkjc.com/en-us/local/information/localresults?racedate=2023%2F12%2F06&Racecourse=HV&RaceNo=7"
  },
  {
    "raceId": "2023-12-06-HV-8",
    "date": "2023-12-06",
    "racecourse": "HV",
    "raceNo": 8,
    "raceIndex": 230,
    "raceClass": 3,
    "distance": 1200,
    "ratingBand": "80-60",
    "surface": "TURF",
    "course": "TURF - \"A\" Course",
    "going": "GOOD",
    "runners": [
      {
        "placing": 1,
        "horseNo": 5,
        "horseId": "HK_2022_H303",
        "brandNo": "H303",
        "horseName": "TOMODACHI KOKOROE",
        "jockey": "C Y Ho",
        "trainer": "D A Hayes",
        "actualWeight": 131,
        "declaredHorseWeight": 1186,
        "draw": 8,
        "lbw": 0,
        "runningPosition": [
          1,
          1,
          1
        ],
        "finishSeconds": 70.19,
        "winOdds": 7.2
      },
      {
        "placing": 2,
        "horseNo": 11,
        "horseId": "HK_2022_H216",
        "brandNo": "H216",
        "horseName": "KAHOLO ANGEL",
        "jockey": "Z Purton",
        "trainer": "C Fownes",
        "actualWeight": 124,
        "declaredHorseWeight": 1103,
        "draw": 2,
        "lbw": 0.5,
        "runningPosition": [
          4,
          4,
          2
        ],
        "finishSeconds": 70.3,
        "winOdds": 4.5
      },
      {
        "placing": 3,
        "horseNo": 10,
        "horseId": "HK_2020_E300",
        "brandNo": "E300",
        "horseName": "TORONADO PHANTOM",
        "jockey": "R King",
        "trainer": "J Size",
        "actualWeight": 125,
        "declaredHorseWeight": 1142,
        "draw": 1,
        "lbw": 1.75,
        "runningPosition": [
          7,
          6,
          3
        ],
        "finishSeconds": 70.48,
        "winOdds": 6
      },
      {
        "placing": 4,
        "horseNo": 9,
        "horseId": "HK_2022_H356",
        "brandNo": "H356",
        "horseName": "GAMEPLAYER ELITE",
        "jockey": "J McDonald",
        "trainer": "D J Whyte",
        "actualWeight": 126,
        "declaredHorseWeight": 1041,
        "draw": 4,
        "lbw": 2.25,
        "runningPosition": [
          5,
          5,
          4
        ],
        "finishSeconds": 70.56,
        "winOdds": 4.3
      },
      {
        "placing": 5,
        "horseNo": 4,
        "horseId": "HK_2020_E447",
        "brandNo": "E447",
        "horseName": "SOLID IMPACT",
        "jockey": "B Murzabayev",
        "trainer": "D J Hall",
        "actualWeight": 132,
        "declaredHorseWeight": 1037,
        "draw": 11,
        "lbw": 3.25,
        "runningPosition": [
          11,
          11,
          5
        ],
        "finishSeconds": 70.7,
        "winOdds": 56
      },
      {
        "placing": 6,
        "horseNo": 8,
        "horseId": "HK_2021_G016",
        "brandNo": "G016",
        "horseName": "SUGAR SUGAR",
        "jockey": "M Barzalona",
        "trainer": "C Fownes",
        "actualWeight": 128,
        "declaredHorseWeight": 1089,
        "draw": 12,
        "lbw": 3.5,
        "runningPosition": [
          3,
          2,
          6
        ],
        "finishSeconds": 70.76,
        "winOdds": 14
      },
      {
        "placing": 7,
        "horseNo": 1,
        "horseId": "HK_2021_G130",
        "brandNo": "G130",
        "horseName": "LIGHTNING BOLT",
        "jockey": "K Teetan",
        "trainer": "C S Shum",
        "actualWeight": 135,
        "declaredHorseWeight": 1166,
        "draw": 3,
        "lbw": 4,
        "runningPosition": [
          8,
          8,
          7
        ],
        "finishSeconds": 70.84,
        "winOdds": 14
      },
      {
        "placing": 8,
        "horseNo": 12,
        "horseId": "HK_2020_E364",
        "brandNo": "E364",
        "horseName": "SOLAR PARTNER",
        "jockey": "R Moore",
        "trainer": "P F Yiu",
        "actualWeight": 124,
        "declaredHorseWeight": 1230,
        "draw": 5,
        "lbw": 4.75,
        "runningPosition": [
          9,
          9,
          8
        ],
        "finishSeconds": 70.94,
        "winOdds": 14
      },
      {
        "placing": 9,
        "horseNo": 6,
        "horseId": "HK_2020_E490",
        "brandNo": "E490",
        "horseName": "GOLDEN EMPIRE",
        "jockey": "T Marquand",
        "trainer": "K W Lui",
        "actualWeight": 130,
        "declaredHorseWeight": 1093,
        "draw": 7,
        "lbw": 4.75,
        "runningPosition": [
          10,
          10,
          9
        ],
        "finishSeconds": 70.94,
        "winOdds": 20
      },
      {
        "placing": 10,
        "horseNo": 2,
        "horseId": "HK_2020_E385",
        "brandNo": "E385",
        "horseName": "LUCKY ARCHANGEL",
        "jockey": "L Hewitson",
        "trainer": "F C Lor",
        "actualWeight": 132,
        "declaredHorseWeight": 1167,
        "draw": 6,
        "lbw": 5,
        "runningPosition": [
          2,
          3,
          10
        ],
        "finishSeconds": 70.99,
        "winOdds": 11
      },
      {
        "placing": 11,
        "horseNo": 3,
        "horseId": "HK_2022_H091",
        "brandNo": "H091",
        "horseName": "SINBA",
        "jockey": "H Doyle",
        "trainer": "J Richards",
        "actualWeight": 132,
        "declaredHorseWeight": 1192,
        "draw": 10,
        "lbw": 6,
        "runningPosition": [
          12,
          12,
          11
        ],
        "finishSeconds": 71.15,
        "winOdds": 18
      },
      {
        "placing": 12,
        "horseNo": 7,
        "horseId": "HK_2020_E459",
        "brandNo": "E459",
        "horseName": "BEAUTY GLORY",
        "jockey": "Y Kawada",
        "trainer": "A S Cruz",
        "actualWeight": 128,
        "declaredHorseWeight": 1185,
        "draw": 9,
        "lbw": 8.25,
        "runningPosition": [
          6,
          7,
          12
        ],
        "finishSeconds": 71.52,
        "winOdds": 31
      }
    ],
    "dividends": {
      "win": [
        {
          "pool": "WIN",
          "combination": [
            5
          ],
          "dividendPer10": 72
        }
      ],
      "place": [
        {
          "pool": "PLACE",
          "combination": [
            5
          ],
          "dividendPer10": 24.5
        },
        {
          "pool": "PLACE",
          "combination": [
            11
          ],
          "dividendPer10": 21.5
        },
        {
          "pool": "PLACE",
          "combination": [
            10
          ],
          "dividendPer10": 19
        }
      ],
      "quinella": [
        {
          "pool": "QUINELLA",
          "combination": [
            5,
            11
          ],
          "dividendPer10": 208.5
        }
      ],
      "quinellaPlace": [
        {
          "pool": "QUINELLA PLACE",
          "combination": [
            5,
            11
          ],
          "dividendPer10": 78
        },
        {
          "pool": "QUINELLA PLACE",
          "combination": [
            5,
            10
          ],
          "dividendPer10": 82
        },
        {
          "pool": "QUINELLA PLACE",
          "combination": [
            10,
            11
          ],
          "dividendPer10": 56.5
        }
      ],
      "forecast": [
        {
          "pool": "FORECAST",
          "combination": [
            5,
            11
          ],
          "dividendPer10": 433
        }
      ],
      "tierce": [
        {
          "pool": "TIERCE",
          "combination": [
            5,
            11,
            10
          ],
          "dividendPer10": 2166
        }
      ],
      "trio": [
        {
          "pool": "TRIO",
          "combination": [
            5,
            10,
            11
          ],
          "dividendPer10": 408
        }
      ],
      "first4": [
        {
          "pool": "FIRST 4",
          "combination": [
            5,
            9,
            10,
            11
          ],
          "dividendPer10": 226
        }
      ],
      "quartet": [
        {
          "pool": "QUARTET",
          "combination": [
            5,
            11,
            10,
            9
          ],
          "dividendPer10": 7094
        }
      ]
    },
    "source": "https://racing.hkjc.com/en-us/local/information/localresults?racedate=2023%2F12%2F06&Racecourse=HV&RaceNo=8"
  },
  {
    "raceId": "2023-12-06-HV-9",
    "date": "2023-12-06",
    "racecourse": "HV",
    "raceNo": 9,
    "raceIndex": 231,
    "raceClass": 2,
    "distance": 1800,
    "ratingBand": "100-80",
    "surface": "TURF",
    "course": "TURF - \"A\" Course",
    "going": "GOOD",
    "runners": [
      {
        "placing": 1,
        "horseNo": 6,
        "horseId": "HK_2022_H215",
        "brandNo": "H215",
        "horseName": "HELENE FEELING",
        "jockey": "J McDonald",
        "trainer": "C S Shum",
        "actualWeight": 124,
        "declaredHorseWeight": 1217,
        "draw": 6,
        "lbw": 0,
        "runningPosition": [
          2,
          4,
          4,
          3,
          1
        ],
        "finishSeconds": 109.53,
        "winOdds": 2.4
      },
      {
        "placing": 2,
        "horseNo": 9,
        "horseId": "HK_2018_C462",
        "brandNo": "C462",
        "horseName": "BUTTERFIELD",
        "jockey": "T Marquand",
        "trainer": "C S Shum",
        "actualWeight": 121,
        "declaredHorseWeight": 1175,
        "draw": 12,
        "lbw": 0.5,
        "runningPosition": [
          7,
          8,
          9,
          8,
          2
        ],
        "finishSeconds": 109.62,
        "winOdds": 27
      },
      {
        "placing": 3,
        "horseNo": 7,
        "horseId": "HK_2022_H139",
        "brandNo": "H139",
        "horseName": "THE BEST PEACH",
        "jockey": "Z Purton",
        "trainer": "A S Cruz",
        "actualWeight": 123,
        "declaredHorseWeight": 1016,
        "draw": 7,
        "lbw": 1.75,
        "runningPosition": [
          11,
          11,
          10,
          10,
          3
        ],
        "finishSeconds": 109.81,
        "winOdds": 6.7
      },
      {
        "placing": 4,
        "horseNo": 11,
        "horseId": "HK_2020_E430",
        "brandNo": "E430",
        "horseName": "NEARLY FINE",
        "jockey": "M L Yeung",
        "trainer": "C Fownes",
        "actualWeight": 118,
        "declaredHorseWeight": 1113,
        "draw": 5,
        "lbw": 2,
        "runningPosition": [
          6,
          7,
          7,
          7,
          4
        ],
        "finishSeconds": 109.86,
        "winOdds": 20
      },
      {
        "placing": 5,
        "horseNo": 1,
        "horseId": "HK_2020_E054",
        "brandNo": "E054",
        "horseName": "TOURBILLON DIAMOND",
        "jockey": "B Avdulla",
        "trainer": "M Newnham",
        "actualWeight": 135,
        "declaredHorseWeight": 1234,
        "draw": 1,
        "lbw": 3.25,
        "runningPosition": [
          9,
          5,
          5,
          5,
          5
        ],
        "finishSeconds": 110.05,
        "winOdds": 17
      },
      {
        "placing": 6,
        "horseNo": 10,
        "horseId": "HK_2022_H265",
        "brandNo": "H265",
        "horseName": "HAMERON",
        "jockey": "L Ferraris",
        "trainer": "K W Lui",
        "actualWeight": 121,
        "declaredHorseWeight": 1044,
        "draw": 10,
        "lbw": 4.5,
        "runningPosition": [
          3,
          2,
          2,
          2,
          6
        ],
        "finishSeconds": 110.24000000000001,
        "winOdds": 9.6
      },
      {
        "placing": 7,
        "horseNo": 4,
        "horseId": "HK_2021_G356",
        "brandNo": "G356",
        "horseName": "SPIRITED EXPRESS",
        "jockey": "H Doyle",
        "trainer": "P F Yiu",
        "actualWeight": 128,
        "declaredHorseWeight": 1179,
        "draw": 2,
        "lbw": 4.5,
        "runningPosition": [
          10,
          10,
          11,
          12,
          7
        ],
        "finishSeconds": 110.25999999999999,
        "winOdds": 10
      },
      {
        "placing": 8,
        "horseNo": 8,
        "horseId": "HK_2018_C465",
        "brandNo": "C465",
        "horseName": "COLUMBUS COUNTY",
        "jockey": "C Y Ho",
        "trainer": "C Fownes",
        "actualWeight": 122,
        "declaredHorseWeight": 1072,
        "draw": 9,
        "lbw": 4.75,
        "runningPosition": [
          5,
          6,
          6,
          6,
          8
        ],
        "finishSeconds": 110.28999999999999,
        "winOdds": 23
      },
      {
        "placing": 9,
        "horseNo": 12,
        "horseId": "HK_2020_E053",
        "brandNo": "E053",
        "horseName": "LOOKING GREAT",
        "jockey": "K Teetan",
        "trainer": "F C Lor",
        "actualWeight": 117,
        "declaredHorseWeight": 1126,
        "draw": 11,
        "lbw": 5.25,
        "runningPosition": [
          8,
          9,
          8,
          9,
          9
        ],
        "finishSeconds": 110.37,
        "winOdds": 57
      },
      {
        "placing": 10,
        "horseNo": 3,
        "horseId": "HK_2020_E365",
        "brandNo": "E365",
        "horseName": "BOURBONAIRE",
        "jockey": "A Hamelin",
        "trainer": "J Size",
        "actualWeight": 129,
        "declaredHorseWeight": 1047,
        "draw": 4,
        "lbw": 6.5,
        "runningPosition": [
          4,
          3,
          3,
          4,
          10
        ],
        "finishSeconds": 110.59,
        "winOdds": 20
      },
      {
        "placing": 11,
        "horseNo": 2,
        "horseId": "HK_2018_C517",
        "brandNo": "C517",
        "horseName": "ALL FOR ST PAUL'S",
        "jockey": "M Barzalona",
        "trainer": "F C Lor",
        "actualWeight": 129,
        "declaredHorseWeight": 1116,
        "draw": 3,
        "lbw": 6.75,
        "runningPosition": [
          1,
          1,
          1,
          1,
          11
        ],
        "finishSeconds": 110.62,
        "winOdds": 24
      },
      {
        "placing": 12,
        "horseNo": 5,
        "horseId": "HK_2021_G209",
        "brandNo": "G209",
        "horseName": "RISING FROM ASHES",
        "jockey": "L Hewitson",
        "trainer": "K W Lui",
        "actualWeight": 125,
        "declaredHorseWeight": 1000,
        "draw": 8,
        "lbw": 9.25,
        "runningPosition": [
          12,
          12,
          12,
          11,
          12
        ],
        "finishSeconds": 111,
        "winOdds": 6.3
      }
    ],
    "dividends": {
      "win": [
        {
          "pool": "WIN",
          "combination": [
            6
          ],
          "dividendPer10": 24
        }
      ],
      "place": [
        {
          "pool": "PLACE",
          "combination": [
            6
          ],
          "dividendPer10": 12.5
        },
        {
          "pool": "PLACE",
          "combination": [
            9
          ],
          "dividendPer10": 55.5
        },
        {
          "pool": "PLACE",
          "combination": [
            7
          ],
          "dividendPer10": 24
        }
      ],
      "quinella": [
        {
          "pool": "QUINELLA",
          "combination": [
            6,
            9
          ],
          "dividendPer10": 319.5
        }
      ],
      "quinellaPlace": [
        {
          "pool": "QUINELLA PLACE",
          "combination": [
            6,
            9
          ],
          "dividendPer10": 114
        },
        {
          "pool": "QUINELLA PLACE",
          "combination": [
            6,
            7
          ],
          "dividendPer10": 37
        },
        {
          "pool": "QUINELLA PLACE",
          "combination": [
            7,
            9
          ],
          "dividendPer10": 237
        }
      ],
      "forecast": [
        {
          "pool": "FORECAST",
          "combination": [
            6,
            9
          ],
          "dividendPer10": 418
        }
      ],
      "tierce": [
        {
          "pool": "TIERCE",
          "combination": [
            6,
            9,
            7
          ],
          "dividendPer10": 2678
        }
      ],
      "trio": [
        {
          "pool": "TRIO",
          "combination": [
            6,
            7,
            9
          ],
          "dividendPer10": 572
        }
      ],
      "first4": [
        {
          "pool": "FIRST 4",
          "combination": [
            6,
            7,
            9,
            11
          ],
          "dividendPer10": 1966
        }
      ],
      "quartet": [
        {
          "pool": "QUARTET",
          "combination": [
            6,
            9,
            7,
            11
          ],
          "dividendPer10": 28488
        }
      ]
    },
    "source": "https://racing.hkjc.com/en-us/local/information/localresults?racedate=2023%2F12%2F06&Racecourse=HV&RaceNo=9"
  }
]
