[
  {
    "raceId": "2026-01-14-HV-1",
    "date": "2026-01-14",
    "racecourse": "HV",
    "raceNo": 1,
    "raceIndex": 345,
    "raceClass": 5,
    "distance": 1200,
    "ratingBand": "40-0",
    "surface": "TURF",
    "course": "TURF - \"B\" Course",
    "going": "GOOD",
    "runners": [
      {
        "placing": 1,
        "horseNo": 3,
        "horseId": "HK_2024_K103",
        "brandNo": "K103",
        "horseName": "BLAZING BEAM",
        "jockey": "R Kingscote",
        "trainer": "K H Ting",
        "actualWeight": 133,
        "declaredHorseWeight": 1094,
        "draw": 5,
        "lbw": 0,
        "runningPosition": [
          6,
          6,
          1
        ],
        "finishSeconds": 69.92,
        "winOdds": 41
      },
      {
        "placing": 2,
        "horseNo": 6,
        "horseId": "HK_2023_J344",
        "brandNo": "J344",
        "horseName": "CONCORDE STAR",
        "jockey": "J Orman",
        "trainer": "Y S Tsui",
        "actualWeight": 131,
        "declaredHorseWeight": 1069,
        "draw": 12,
        "lbw": 1,
        "runningPosition": [
          7,
          8,
          2
        ],
        "finishSeconds": 70.06,
        "winOdds": 12
      },
      {
        "placing": 3,
        "horseNo": 4,
        "horseId": "HK_2023_J545",
        "brandNo": "J545",
        "horseName": "HAPPY BOYS",
        "jockey": "Z Purton",
        "trainer": "M Newnham",
        "actualWeight": 133,
        "declaredHorseWeight": 1052,
        "draw": 9,
        "lbw": 1.75,
        "runningPosition": [
          10,
          11,
          3
        ],
        "finishSeconds": 70.16,
        "winOdds": 6.7
      },
      {
        "placing": 4,
        "horseNo": 8,
        "horseId": "HK_2024_K028",
        "brandNo": "K028",
        "horseName": "ORIENTAL SURPRISE",
        "jockey": "B Avdulla",
        "trainer": "D A Hayes",
        "actualWeight": 126,
        "declaredHorseWeight": 1078,
        "draw": 1,
        "lbw": 1.75,
        "runningPosition": [
          5,
          5,
          4
        ],
        "finishSeconds": 70.17,
        "winOdds": 4.8
      },
      {
        "placing": 5,
        "horseNo": 9,
        "horseId": "HK_2023_J441",
        "brandNo": "J441",
        "horseName": "BRILLIANT FIRE",
        "jockey": "A Atzeni",
        "trainer": "D J Whyte",
        "actualWeight": 125,
        "declaredHorseWeight": 1177,
        "draw": 4,
        "lbw": 2,
        "runningPosition": [
          2,
          3,
          5
        ],
        "finishSeconds": 70.25,
        "winOdds": 29
      },
      {
        "placing": 6,
        "horseNo": 1,
        "horseId": "HK_2023_J304",
        "brandNo": "J304",
        "horseName": "NEBRASKAN",
        "jockey": "D B McMonagle",
        "trainer": "J Size",
        "actualWeight": 135,
        "declaredHorseWeight": 1045,
        "draw": 11,
        "lbw": 2.5,
        "runningPosition": [
          4,
          2,
          6
        ],
        "finishSeconds": 70.3,
        "winOdds": 5.5
      },
      {
        "placing": 7,
        "horseNo": 10,
        "horseId": "HK_2023_J338",
        "brandNo": "J338",
        "horseName": "LUCKY GENERATIONS",
        "jockey": "H Bowman",
        "trainer": "C Fownes",
        "actualWeight": 124,
        "declaredHorseWeight": 1060,
        "draw": 3,
        "lbw": 2.75,
        "runningPosition": [
          9,
          10,
          7
        ],
        "finishSeconds": 70.35,
        "winOdds": 4.1
      },
      {
        "placing": 8,
        "horseNo": 5,
        "horseId": "HK_2022_H173",
        "brandNo": "H173",
        "horseName": "PODIUM",
        "jockey": "C L Chau",
        "trainer": "D Eustace",
        "actualWeight": 130,
        "declaredHorseWeight": 1067,
        "draw": 7,
        "lbw": 3.25,
        "runningPosition": [
          11,
          9,
          8
        ],
        "finishSeconds": 70.45,
        "winOdds": 8.2
      },
      {
        "placing": 9,
        "horseNo": 7,
        "horseId": "HK_2023_J319",
        "brandNo": "J319",
        "horseName": "CHILL MASTER",
        "jockey": "C Y Ho",
        "trainer": "K L Man",
        "actualWeight": 130,
        "declaredHorseWeight": 1014,
        "draw": 2,
        "lbw": 3.5,
        "runningPosition": [
          8,
          7,
          9
        ],
        "finishSeconds": 70.48,
        "winOdds": 16
      },
      {
        "placing": 10,
        "horseNo": 12,
        "horseId": "HK_2023_J179",
        "brandNo": "J179",
        "horseName": "EVER SMART",
        "jockey": "H T Mo",
        "trainer": "F C Lor",
        "actualWeight": 113,
        "declaredHorseWeight": 1170,
        "draw": 10,
        "lbw": 3.75,
        "runningPosition": [
          12,
          12,
          10
        ],
        "finishSeconds": 70.5,
        "winOdds": 21
      },
      {
        "placing": 11,
        "horseNo": 2,
        "horseId": "HK_2024_K171",
        "brandNo": "K171",
        "horseName": "MULTIDUTCH",
        "jockey": "Y L Chung",
        "trainer": "A S Cruz",
        "actualWeight": 132,
        "declaredHorseWeight": 1039,
        "draw": 6,
        "lbw": 7.5,
        "runningPosition": [
          3,
          4,
          11
        ],
        "finishSeconds": 71.1,
        "winOdds": 31
      },
      {
        "placing": 12,
        "horseNo": 11,
        "horseId": "HK_2019_D090",
        "brandNo": "D090",
        "horseName": "COLONEL",
        "jockey": "K Teetan",
        "trainer": "J Richards",
        "actualWeight": 118,
        "declaredHorseWeight": 1180,
        "draw": 8,
        "lbw": 20,
        "runningPosition": [
          1,
          1,
          12
        ],
        "finishSeconds": 73.11,
        "winOdds": 29
      }
    ],
    "dividends": {
      "win": [
        {
          "pool": "WIN",
          "combination": [
            3
          ],
          "dividendPer10": 419
        }
      ],
      "place": [
        {
          "pool": "PLACE",
          "combination": [
            3
          ],
          "dividendPer10": 106
        },
        {
          "pool": "PLACE",
          "combination": [
            6
          ],
          "dividendPer10": 37.5
        },
        {
          "pool": "PLACE",
          "combination": [
            4
          ],
          "dividendPer10": 23.5
        }
      ],
      "quinella": [
        {
          "pool": "QUINELLA",
          "combination": [
            3,
            6
          ],
          "dividendPer10": 3495
        }
      ],
      "quinellaPlace": [
        {
          "pool": "QUINELLA PLACE",
          "combination": [
            3,
            6
          ],
          "dividendPer10": 856.5
        },
        {
          "pool": "QUINELLA PLACE",
          "combination": [
            3,
            4
          ],
          "dividendPer10": 515.5
        },
        {
          "pool": "QUINELLA PLACE",
          "combination": [
            4,
            6
          ],
          "dividendPer10": 137
        }
      ],
      "forecast": [
        {
          "pool": "FORECAST",
          "combination": [
            3,
            6
          ],
          "dividendPer10": 6719
        }
      ],
      "tierce": [
        {
          "pool": "TIERCE",
          "combination": [
            3,
            6,
            4
          ],
          "dividendPer10": 34297
        }
      ],
      "trio": [
        {
          "pool": "TRIO",
          "combination": [
            3,
            4,
            6
          ],
          "dividendPer10": 4552
        }
      ],
      "first4": [
        {
          "pool": "FIRST 4",
          "combination": [
            3,
            4,
            6,
            8
          ],
          "dividendPer10": 7131
        }
      ],
      "quartet": [
        {
          "pool": "QUARTET",
          "combination": [
            3,
            6,
            4,
            8
          ],
          "dividendPer10": 297528
        }
      ]
    },
    "source": "https://racing.hkjc.com/en-us/local/information/localresults?racedate=2026%2F01%2F14&Racecourse=HV&RaceNo=1"
  },
  {
    "raceId": "2026-01-14-HV-2",
    "date": "2026-01-14",
    "racecourse": "HV",
    "raceNo": 2,
    "raceIndex": 346,
    "raceClass": 4,
    "distance": 1650,
    "ratingBand": "60-40",
    "surface": "TURF",
    "course": "TURF - \"B\" Course",
    "going": "GOOD",
    "runners": [
      {
        "placing": 1,
        "horseNo": 1,
        "horseId": "HK_2023_J446",
        "brandNo": "J446",
        "horseName": "FORTUNATE SON",
        "jockey": "H Bowman",
        "trainer": "W K Mo",
        "actualWeight": 135,
        "declaredHorseWeight": 1130,
        "draw": 7,
        "lbw": 0,
        "runningPosition": [
          8,
          8,
          7,
          1
        ],
        "finishSeconds": 100.03,
        "winOdds": 4.4
      },
      {
        "placing": 2,
        "horseNo": 8,
        "horseId": "HK_2024_K319",
        "brandNo": "K319",
        "horseName": "INNO SUPER",
        "jockey": "C L Chau",
        "trainer": "D Eustace",
        "actualWeight": 121,
        "declaredHorseWeight": 1151,
        "draw": 9,
        "lbw": 1.25,
        "runningPosition": [
          10,
          10,
          9,
          2
        ],
        "finishSeconds": 100.2,
        "winOdds": 8.8
      },
      {
        "placing": 3,
        "horseNo": 10,
        "horseId": "HK_2021_G095",
        "brandNo": "G095",
        "horseName": "SETANTA",
        "jockey": "A Atzeni",
        "trainer": "M Newnham",
        "actualWeight": 120,
        "declaredHorseWeight": 1209,
        "draw": 4,
        "lbw": 1.75,
        "runningPosition": [
          7,
          7,
          8,
          3
        ],
        "finishSeconds": 100.28999999999999,
        "winOdds": 10
      },
      {
        "placing": 4,
        "horseNo": 6,
        "horseId": "HK_2022_H344",
        "brandNo": "H344",
        "horseName": "PING HAI COMET",
        "jockey": "B Avdulla",
        "trainer": "J Size",
        "actualWeight": 126,
        "declaredHorseWeight": 1184,
        "draw": 1,
        "lbw": 2.5,
        "runningPosition": [
          4,
          3,
          3,
          4
        ],
        "finishSeconds": 100.44,
        "winOdds": 14
      },
      {
        "placing": 5,
        "horseNo": 5,
        "horseId": "HK_2024_K039",
        "brandNo": "K039",
        "horseName": "ABSOLUTE AWAKENED",
        "jockey": "Z Purton",
        "trainer": "F C Lor",
        "actualWeight": 128,
        "declaredHorseWeight": 1098,
        "draw": 11,
        "lbw": 3.25,
        "runningPosition": [
          2,
          2,
          2,
          5
        ],
        "finishSeconds": 100.53999999999999,
        "winOdds": 6.6
      },
      {
        "placing": 6,
        "horseNo": 2,
        "horseId": "HK_2024_K382",
        "brandNo": "K382",
        "horseName": "ALL ROUND WINNER",
        "jockey": "H Bentley",
        "trainer": "D A Hayes",
        "actualWeight": 131,
        "declaredHorseWeight": 1146,
        "draw": 6,
        "lbw": 3.5,
        "runningPosition": [
          6,
          6,
          6,
          6
        ],
        "finishSeconds": 100.58,
        "winOdds": 5
      },
      {
        "placing": 7,
        "horseNo": 3,
        "horseId": "HK_2021_G125",
        "brandNo": "G125",
        "horseName": "SURE JOYFUL",
        "jockey": "M Guyon",
        "trainer": "P F Yiu",
        "actualWeight": 131,
        "declaredHorseWeight": 1088,
        "draw": 12,
        "lbw": 4,
        "runningPosition": [
          11,
          11,
          11,
          7
        ],
        "finishSeconds": 100.65,
        "winOdds": 26
      },
      {
        "placing": 8,
        "horseNo": 12,
        "horseId": "HK_2024_K073",
        "brandNo": "K073",
        "horseName": "LUCKY BLESSING",
        "jockey": "Y L Chung",
        "trainer": "W K Mo",
        "actualWeight": 113,
        "declaredHorseWeight": 1080,
        "draw": 3,
        "lbw": 4.25,
        "runningPosition": [
          1,
          1,
          1,
          8
        ],
        "finishSeconds": 100.69,
        "winOdds": 6.3
      },
      {
        "placing": 9,
        "horseNo": 9,
        "horseId": "HK_2021_G307",
        "brandNo": "G307",
        "horseName": "PRINCE ALEX",
        "jockey": "R Kingscote",
        "trainer": "D J Whyte",
        "actualWeight": 120,
        "declaredHorseWeight": 1086,
        "draw": 2,
        "lbw": 4.75,
        "runningPosition": [
          5,
          5,
          5,
          9
        ],
        "finishSeconds": 100.78999999999999,
        "winOdds": 22
      },
      {
        "placing": 10,
        "horseNo": 7,
        "horseId": "HK_2023_J503",
        "brandNo": "J503",
        "horseName": "SOMELOVEFROMABOVE",
        "jockey": "M Chadwick",
        "trainer": "C Fownes",
        "actualWeight": 122,
        "declaredHorseWeight": 1185,
        "draw": 5,
        "lbw": 5,
        "runningPosition": [
          3,
          4,
          4,
          10
        ],
        "finishSeconds": 100.82,
        "winOdds": 24
      },
      {
        "placing": 11,
        "horseNo": 11,
        "horseId": "HK_2021_E496",
        "brandNo": "E496",
        "horseName": "MANAGEMENT FOLKS",
        "jockey": "M F Poon",
        "trainer": "D J Hall",
        "actualWeight": 119,
        "declaredHorseWeight": 1172,
        "draw": 8,
        "lbw": 5.5,
        "runningPosition": [
          12,
          12,
          12,
          11
        ],
        "finishSeconds": 100.91,
        "winOdds": 30
      },
      {
        "placing": 12,
        "horseNo": 4,
        "horseId": "HK_2021_G150",
        "brandNo": "G150",
        "horseName": "TURIN WARRIOR",
        "jockey": "C Y Ho",
        "trainer": "K L Man",
        "actualWeight": 129,
        "declaredHorseWeight": 1132,
        "draw": 10,
        "lbw": 5.75,
        "runningPosition": [
          9,
          9,
          10,
          12
        ],
        "finishSeconds": 100.96000000000001,
        "winOdds": 23
      }
    ],
    "dividends": {
      "win": [
        {
          "pool": "WIN",
          "combination": [
            1
          ],
          "dividendPer10": 44
        }
      ],
      "place": [
        {
          "pool": "PLACE",
          "combination": [
            1
          ],
          "dividendPer10": 18.5
        },
        {
          "pool": "PLACE",
          "combination": [
            8
          ],
          "dividendPer10": 28.5
        },
        {
          "pool": "PLACE",
          "combination": [
            10
          ],
          "dividendPer10": 26
        }
      ],
      "quinella": [
        {
          "pool": "QUINELLA",
          "combination": [
            1,
            8
          ],
          "dividendPer10": 225.5
        }
      ],
      "quinellaPlace": [
        {
          "pool": "QUINELLA PLACE",
          "combination": [
            1,
            8
          ],
          "dividendPer10": 80
        },
        {
          "pool": "QUINELLA PLACE",
          "combination": [
            1,
            10
          ],
          "dividendPer10": 67
        },
        {
          "pool": "QUINELLA PLACE",
          "combination": [
            8,
            10
          ],
          "dividendPer10": 143.5
        }
      ],
      "forecast": [
        {
          "pool": "FORECAST",
          "combination": [
            1,
            8
          ],
          "dividendPer10": 441
        }
      ],
      "tierce": [
        {
          "pool": "TIERCE",
          "combination": [
            1,
            8,
            10
          ],
          "dividendPer10": 3107
        }
      ],
      "trio": [
        {
          "pool": "TRIO",
          "combination": [
            1,
            8,
            10
          ],
          "dividendPer10": 671
        }
      ],
      "first4": [
        {
          "pool": "FIRST 4",
          "combination": [
            1,
            6,
            8,
            10
          ],
          "dividendPer10": 1786
        }
      ],
      "quartet": [
        {
          "pool": "QUARTET",
          "combination": [
            1,
            8,
            10,
            6
          ],
          "dividendPer10": 29824
        }
      ]
    },
    "source": "https://racing.hkjc.com/en-us/local/information/localresults?racedate=2026%2F01%2F14&Racecourse=HV&RaceNo=2"
  },
  {
    "raceId": "2026-01-14-HV-3",
    "date": "2026-01-14",
    "racecourse": "HV",
    "raceNo": 3,
    "raceIndex": 347,
    "raceClass": 4,
    "distance": 1200,
    "ratingBand": "60-40",
    "surface": "TURF",
    "course": "TURF - \"B\" Course",
    "going": "GOOD",
    "runners": [
      {
        "placing": 1,
        "horseNo": 1,
        "horseId": "HK_2022_H235",
        "brandNo": "H235",
        "horseName": "LUCKY PLANET",
        "jockey": "M F Poon",
        "trainer": "W K Mo",
        "actualWeight": 135,
        "declaredHorseWeight": 1103,
        "draw": 6,
        "lbw": 0,
        "runningPosition": [
          1,
          1,
          1
        ],
        "finishSeconds": 69.37,
        "winOdds": 9.6
      },
      {
        "placing": 2,
        "horseNo": 5,
        "horseId": "HK_2023_J362",
        "brandNo": "J362",
        "horseName": "BITS SUPERSTAR",
        "jockey": "Z Purton",
        "trainer": "D J Hall",
        "actualWeight": 127,
        "declaredHorseWeight": 1073,
        "draw": 10,
        "lbw": 2.75,
        "runningPosition": [
          2,
          2,
          2
        ],
        "finishSeconds": 69.82,
        "winOdds": 12
      },
      {
        "placing": 3,
        "horseNo": 11,
        "horseId": "HK_2023_J243",
        "brandNo": "J243",
        "horseName": "CALL TO COMMAND",
        "jockey": "M Guyon",
        "trainer": "C W Chang",
        "actualWeight": 119,
        "declaredHorseWeight": 1265,
        "draw": 8,
        "lbw": 3.25,
        "runningPosition": [
          5,
          5,
          3
        ],
        "finishSeconds": 69.87,
        "winOdds": 29
      },
      {
        "placing": 4,
        "horseNo": 4,
        "horseId": "HK_2024_K451",
        "brandNo": "K451",
        "horseName": "GIANT BALLON",
        "jockey": "L Hewitson",
        "trainer": "D J Whyte",
        "actualWeight": 128,
        "declaredHorseWeight": 1130,
        "draw": 11,
        "lbw": 3.25,
        "runningPosition": [
          9,
          8,
          4
        ],
        "finishSeconds": 69.89,
        "winOdds": 11
      },
      {
        "placing": 5,
        "horseNo": 2,
        "horseId": "HK_2024_K301",
        "brandNo": "K301",
        "horseName": "GOOD LUCK HAPPY",
        "jockey": "Y L Chung",
        "trainer": "A S Cruz",
        "actualWeight": 128,
        "declaredHorseWeight": 1117,
        "draw": 1,
        "lbw": 4,
        "runningPosition": [
          3,
          3,
          5
        ],
        "finishSeconds": 69.99,
        "winOdds": 4.1
      },
      {
        "placing": 6,
        "horseNo": 10,
        "horseId": "HK_2024_K422",
        "brandNo": "K422",
        "horseName": "WINNING CIGAR",
        "jockey": "H Bentley",
        "trainer": "D A Hayes",
        "actualWeight": 120,
        "declaredHorseWeight": 1078,
        "draw": 2,
        "lbw": 4,
        "runningPosition": [
          4,
          4,
          6
        ],
        "finishSeconds": 70.02,
        "winOdds": 37
      },
      {
        "placing": 7,
        "horseNo": 9,
        "horseId": "HK_2024_K402",
        "brandNo": "K402",
        "horseName": "THE ALL ROUNDER",
        "jockey": "K Teetan",
        "trainer": "P C Ng",
        "actualWeight": 121,
        "declaredHorseWeight": 1038,
        "draw": 9,
        "lbw": 5.5,
        "runningPosition": [
          11,
          11,
          7
        ],
        "finishSeconds": 70.24,
        "winOdds": 55
      },
      {
        "placing": 8,
        "horseNo": 3,
        "horseId": "HK_2024_K417",
        "brandNo": "K417",
        "horseName": "NEVER SETTLE",
        "jockey": "C Y Ho",
        "trainer": "K W Lui",
        "actualWeight": 129,
        "declaredHorseWeight": 1149,
        "draw": 3,
        "lbw": 5.75,
        "runningPosition": [
          8,
          9,
          8
        ],
        "finishSeconds": 70.28999999999999,
        "winOdds": 2.8
      },
      {
        "placing": 9,
        "horseNo": 7,
        "horseId": "HK_2024_K532",
        "brandNo": "K532",
        "horseName": "WINNING NOW",
        "jockey": "K C Leung",
        "trainer": "F C Lor",
        "actualWeight": 124,
        "declaredHorseWeight": 1105,
        "draw": 7,
        "lbw": 6,
        "runningPosition": [
          7,
          7,
          9
        ],
        "finishSeconds": 70.31,
        "winOdds": 15
      },
      {
        "placing": 10,
        "horseNo": 12,
        "horseId": "HK_2024_K051",
        "brandNo": "K051",
        "horseName": "SONIC PURSUIT",
        "jockey": "A Badel",
        "trainer": "J Richards",
        "actualWeight": 118,
        "declaredHorseWeight": 1266,
        "draw": 4,
        "lbw": 7,
        "runningPosition": [
          10,
          10,
          10
        ],
        "finishSeconds": 70.5,
        "winOdds": 6.7
      },
      {
        "placing": 11,
        "horseNo": 6,
        "horseId": "HK_2024_K503",
        "brandNo": "K503",
        "horseName": "FALCON HUNTER",
        "jockey": "C L Chau",
        "trainer": "C H Yip",
        "actualWeight": 122,
        "declaredHorseWeight": 1106,
        "draw": 12,
        "lbw": 7.25,
        "runningPosition": [
          12,
          12,
          11
        ],
        "finishSeconds": 70.52,
        "winOdds": 29
      },
      {
        "placing": 12,
        "horseNo": 8,
        "horseId": "HK_2024_K219",
        "brandNo": "K219",
        "horseName": "THE PROMISE",
        "jockey": "H T Mo",
        "trainer": "W Y So",
        "actualWeight": 120,
        "declaredHorseWeight": 1196,
        "draw": 5,
        "lbw": 14.5,
        "runningPosition": [
          6,
          6,
          12
        ],
        "finishSeconds": 71.67,
        "winOdds": 73
      }
    ],
    "dividends": {
      "win": [
        {
          "pool": "WIN",
          "combination": [
            1
          ],
          "dividendPer10": 96
        }
      ],
      "place": [
        {
          "pool": "PLACE",
          "combination": [
            1
          ],
          "dividendPer10": 29.5
        },
        {
          "pool": "PLACE",
          "combination": [
            5
          ],
          "dividendPer10": 35
        },
        {
          "pool": "PLACE",
          "combination": [
            11
          ],
          "dividendPer10": 59.5
        }
      ],
      "quinella": [
        {
          "pool": "QUINELLA",
          "combination": [
            1,
            5
          ],
          "dividendPer10": 506
        }
      ],
      "quinellaPlace": [
        {
          "pool": "QUINELLA PLACE",
          "combination": [
            1,
            5
          ],
          "dividendPer10": 137.5
        },
        {
          "pool": "QUINELLA PLACE",
          "combination": [
            1,
            11
          ],
          "dividendPer10": 382.5
        },
        {
          "pool": "QUINELLA PLACE",
          "combination": [
            5,
            11
          ],
          "dividendPer10": 419.5
        }
      ],
      "forecast": [
        {
          "pool": "FORECAST",
          "combination": [
            1,
            5
          ],
          "dividendPer10": 875
        }
      ],
      "tierce": [
        {
          "pool": "TIERCE",
          "combination": [
            1,
            5,
            11
          ],
          "dividendPer10": 17992
        }
      ],
      "trio": [
        {
          "pool": "TRIO",
          "combination": [
            1,
            5,
            11
          ],
          "dividendPer10": 4092
        }
      ],
      "first4": [
        {
          "pool": "FIRST 4",
          "combination": [
            1,
            4,
            5,
            11
          ],
          "dividendPer10": 5013
        }
      ],
      "quartet": [
        {
          "pool": "QUARTET",
          "combination": [
            1,
            5,
            11,
            4
          ],
          "dividendPer10": 102102
        }
      ]
    },
    "source": "https://racing.hkjc.com/en-us/local/information/localresults?racedate=2026%2F01%2F14&Racecourse=HV&RaceNo=3"
  },
  {
    "raceId": "2026-01-14-HV-4",
    "date": "2026-01-14",
    "racecourse": "HV",
    "raceNo": 4,
    "raceIndex": 348,
    "raceClass": 4,
    "distance": 1650,
    "ratingBand": "60-40",
    "surface": "TURF",
    "course": "TURF - \"B\" Course",
    "going": "GOOD",
    "runners": [
      {
        "placing": 1,
        "horseNo": 6,
        "horseId": "HK_2024_K003",
        "brandNo": "K003",
        "horseName": "FORTUNE STAR",
        "jockey": "L Ferraris",
        "trainer": "M Newnham",
        "actualWeight": 123,
        "declaredHorseWeight": 1134,
        "draw": 9,
        "lbw": 0,
        "runningPosition": [
          9,
          9,
          11,
          1
        ],
        "finishSeconds": 99.97999999999999,
        "winOdds": 6.1
      },
      {
        "placing": 2,
        "horseNo": 8,
        "horseId": "HK_2024_K343",
        "brandNo": "K343",
        "horseName": "INCANTO STAR",
        "jockey": "Z Purton",
        "trainer": "D J Hall",
        "actualWeight": 122,
        "declaredHorseWeight": 1029,
        "draw": 4,
        "lbw": 1.25,
        "runningPosition": [
          6,
          7,
          8,
          2
        ],
        "finishSeconds": 100.17,
        "winOdds": 9.2
      },
      {
        "placing": 3,
        "horseNo": 4,
        "horseId": "HK_2023_J132",
        "brandNo": "J132",
        "horseName": "CALIFORNIA BANNER",
        "jockey": "M Chadwick",
        "trainer": "W K Mo",
        "actualWeight": 121,
        "declaredHorseWeight": 1168,
        "draw": 8,
        "lbw": 1.5,
        "runningPosition": [
          8,
          8,
          7,
          3
        ],
        "finishSeconds": 100.21000000000001,
        "winOdds": 5.6
      },
      {
        "placing": 4,
        "horseNo": 9,
        "horseId": "HK_2023_J213",
        "brandNo": "J213",
        "horseName": "SMART CITY",
        "jockey": "M F Poon",
        "trainer": "P F Yiu",
        "actualWeight": 121,
        "declaredHorseWeight": 1144,
        "draw": 1,
        "lbw": 3.25,
        "runningPosition": [
          4,
          5,
          5,
          4
        ],
        "finishSeconds": 100.49000000000001,
        "winOdds": 18
      },
      {
        "placing": 5,
        "horseNo": 7,
        "horseId": "HK_2023_J135",
        "brandNo": "J135",
        "horseName": "GOOD LUCK WIN",
        "jockey": "Y L Chung",
        "trainer": "K H Ting",
        "actualWeight": 121,
        "declaredHorseWeight": 1096,
        "draw": 12,
        "lbw": 3.5,
        "runningPosition": [
          2,
          2,
          2,
          5
        ],
        "finishSeconds": 100.53999999999999,
        "winOdds": 15
      },
      {
        "placing": 6,
        "horseNo": 2,
        "horseId": "HK_2022_H324",
        "brandNo": "H324",
        "horseName": "NOBLE PURSUIT",
        "jockey": "H Bowman",
        "trainer": "C Fownes",
        "actualWeight": 133,
        "declaredHorseWeight": 1210,
        "draw": 11,
        "lbw": 4,
        "runningPosition": [
          12,
          12,
          10,
          6
        ],
        "finishSeconds": 100.61,
        "winOdds": 18
      },
      {
        "placing": 7,
        "horseNo": 3,
        "horseId": "HK_2023_J137",
        "brandNo": "J137",
        "horseName": "GLORIOUS JOURNEY",
        "jockey": "C Y Ho",
        "trainer": "F C Lor",
        "actualWeight": 131,
        "declaredHorseWeight": 1062,
        "draw": 2,
        "lbw": 5,
        "runningPosition": [
          11,
          11,
          9,
          7
        ],
        "finishSeconds": 100.78999999999999,
        "winOdds": 6.2
      },
      {
        "placing": 8,
        "horseNo": 10,
        "horseId": "HK_2023_J488",
        "brandNo": "J488",
        "horseName": "NORTHERN FIRE BALL",
        "jockey": "E C W Wong",
        "trainer": "C H Yip",
        "actualWeight": 125,
        "declaredHorseWeight": 1127,
        "draw": 7,
        "lbw": 5.25,
        "runningPosition": [
          1,
          1,
          1,
          8
        ],
        "finishSeconds": 100.82,
        "winOdds": 21
      },
      {
        "placing": 9,
        "horseNo": 11,
        "horseId": "HK_2023_J541",
        "brandNo": "J541",
        "horseName": "CONSPIRACY WITNESS",
        "jockey": "H Bentley",
        "trainer": "D A Hayes",
        "actualWeight": 118,
        "declaredHorseWeight": 1119,
        "draw": 5,
        "lbw": 5.5,
        "runningPosition": [
          7,
          6,
          6,
          9
        ],
        "finishSeconds": 100.85,
        "winOdds": 6
      },
      {
        "placing": 10,
        "horseNo": 1,
        "horseId": "HK_2023_J266",
        "brandNo": "J266",
        "horseName": "HARMONY GALAXY",
        "jockey": "R Kingscote",
        "trainer": "C S Shum",
        "actualWeight": 135,
        "declaredHorseWeight": 1032,
        "draw": 10,
        "lbw": 6.75,
        "runningPosition": [
          10,
          10,
          12,
          10
        ],
        "finishSeconds": 101.06,
        "winOdds": 16
      },
      {
        "placing": 11,
        "horseNo": 12,
        "horseId": "HK_2022_H277",
        "brandNo": "H277",
        "horseName": "SHINKANSEN",
        "jockey": "L Hewitson",
        "trainer": "D J Whyte",
        "actualWeight": 117,
        "declaredHorseWeight": 1171,
        "draw": 3,
        "lbw": 8.5,
        "runningPosition": [
          3,
          3,
          3,
          11
        ],
        "finishSeconds": 101.35,
        "winOdds": 9.9
      },
      {
        "placing": 12,
        "horseNo": 5,
        "horseId": "HK_2021_G465",
        "brandNo": "G465",
        "horseName": "FORERUNNER",
        "jockey": "M Guyon",
        "trainer": "W K Mo",
        "actualWeight": 128,
        "declaredHorseWeight": 1060,
        "draw": 6,
        "lbw": 10,
        "runningPosition": [
          5,
          4,
          4,
          12
        ],
        "finishSeconds": 101.59,
        "winOdds": 18
      }
    ],
    "dividends": {
      "win": [
        {
          "pool": "WIN",
          "combination": [
            6
          ],
          "dividendPer10": 61
        }
      ],
      "place": [
        {
          "pool": "PLACE",
          "combination": [
            6
          ],
          "dividendPer10": 20
        },
        {
          "pool": "PLACE",
          "combination": [
            8
          ],
          "dividendPer10": 31.5
        },
        {
          "pool": "PLACE",
          "combination": [
            4
          ],
          "dividendPer10": 20.5
        }
      ],
      "quinella": [
        {
          "pool": "QUINELLA",
          "combination": [
            6,
            8
          ],
          "dividendPer10": 312.5
        }
      ],
      "quinellaPlace": [
        {
          "pool": "QUINELLA PLACE",
          "combination": [
            6,
            8
          ],
          "dividendPer10": 90
        },
        {
          "pool": "QUINELLA PLACE",
          "combination": [
            4,
            6
          ],
          "dividendPer10": 94
        },
        {
          "pool": "QUINELLA PLACE",
          "combination": [
            4,
            8
          ],
          "dividendPer10": 128
        }
      ],
      "forecast": [
        {
          "pool": "FORECAST",
          "combination": [
            6,
            8
          ],
          "dividendPer10": 449
        }
      ],
      "tierce": [
        {
          "pool": "TIERCE",
          "combination": [
            6,
            8,
            4
          ],
          "dividendPer10": 5496
        }
      ],
      "trio": [
        {
          "pool": "TRIO",
          "combination": [
            4,
            6,
            8
          ],
          "dividendPer10": 1088
        }
      ],
      "first4": [
        {
          "pool": "FIRST 4",
          "combination": [
            4,
            6,
            8,
            9
          ],
          "dividendPer10": 3351
        }
      ],
      "quartet": [
        {
          "pool": "QUARTET",
          "combination": [
            6,
            8,
            4,
            9
          ],
          "dividendPer10": 84753
        }
      ]
    },
    "source": "https://racing.hkjc.com/en-us/local/information/localresults?racedate=2026%2F01%2F14&Racecourse=HV&RaceNo=4"
  },
  {
    "raceId": "2026-01-14-HV-5",
    "date": "2026-01-14",
    "racecourse": "HV",
    "raceNo": 5,
    "raceIndex": 349,
    "raceClass": 3,
    "distance": 1650,
    "ratingBand": "85-60",
    "surface": "TURF",
    "course": "TURF - \"B\" Course",
    "going": "GOOD",
    "runners": [
      {
        "placing": 1,
        "horseNo": 6,
        "horseId": "HK_2023_J514",
        "brandNo": "J514",
        "horseName": "MAX QUE",
        "jockey": "Z Purton",
        "trainer": "M Newnham",
        "actualWeight": 122,
        "declaredHorseWeight": 1124,
        "draw": 3,
        "lbw": 0,
        "runningPosition": [
          5,
          5,
          6,
          1
        ],
        "finishSeconds": 100.57,
        "winOdds": 1.7
      },
      {
        "placing": 2,
        "horseNo": 3,
        "horseId": "HK_2024_K057",
        "brandNo": "K057",
        "horseName": "SILVERY BREEZE",
        "jockey": "H Bowman",
        "trainer": "D Eustace",
        "actualWeight": 132,
        "declaredHorseWeight": 1128,
        "draw": 12,
        "lbw": 1.25,
        "runningPosition": [
          11,
          11,
          12,
          2
        ],
        "finishSeconds": 100.77000000000001,
        "winOdds": 4.6
      },
      {
        "placing": 3,
        "horseNo": 9,
        "horseId": "HK_2023_J396",
        "brandNo": "J396",
        "horseName": "THRIVING BROTHERS",
        "jockey": "M Chadwick",
        "trainer": "C H Yip",
        "actualWeight": 119,
        "declaredHorseWeight": 1139,
        "draw": 11,
        "lbw": 1.5,
        "runningPosition": [
          1,
          1,
          1,
          3
        ],
        "finishSeconds": 100.83,
        "winOdds": 38
      },
      {
        "placing": 4,
        "horseNo": 7,
        "horseId": "HK_2023_J079",
        "brandNo": "J079",
        "horseName": "VIVA GRACIOUSNESS",
        "jockey": "A Badel",
        "trainer": "A S Cruz",
        "actualWeight": 121,
        "declaredHorseWeight": 1097,
        "draw": 8,
        "lbw": 2.25,
        "runningPosition": [
          8,
          8,
          7,
          4
        ],
        "finishSeconds": 100.95,
        "winOdds": 36
      },
      {
        "placing": 5,
        "horseNo": 1,
        "horseId": "HK_2024_K076",
        "brandNo": "K076",
        "horseName": "THE BOOM BOX",
        "jockey": "C Y Ho",
        "trainer": "W Y So",
        "actualWeight": 135,
        "declaredHorseWeight": 1114,
        "draw": 5,
        "lbw": 3.75,
        "runningPosition": [
          10,
          10,
          8,
          5
        ],
        "finishSeconds": 101.18,
        "winOdds": 19
      },
      {
        "placing": 6,
        "horseNo": 8,
        "horseId": "HK_2022_H070",
        "brandNo": "H070",
        "horseName": "SAMARKAND",
        "jockey": "L Hewitson",
        "trainer": "D A Hayes",
        "actualWeight": 120,
        "declaredHorseWeight": 1192,
        "draw": 1,
        "lbw": 3.75,
        "runningPosition": [
          3,
          3,
          4,
          6
        ],
        "finishSeconds": 101.19,
        "winOdds": 20
      },
      {
        "placing": 7,
        "horseNo": 10,
        "horseId": "HK_2023_J486",
        "brandNo": "J486",
        "horseName": "CHILL KAKA",
        "jockey": "M F Poon",
        "trainer": "P F Yiu",
        "actualWeight": 118,
        "declaredHorseWeight": 1102,
        "draw": 4,
        "lbw": 4,
        "runningPosition": [
          2,
          2,
          2,
          7
        ],
        "finishSeconds": 101.22999999999999,
        "winOdds": 18
      },
      {
        "placing": 8,
        "horseNo": 11,
        "horseId": "HK_2022_H289",
        "brandNo": "H289",
        "horseName": "AESTHETICISM",
        "jockey": "K Teetan",
        "trainer": "P C Ng",
        "actualWeight": 115,
        "declaredHorseWeight": 1066,
        "draw": 6,
        "lbw": 4.5,
        "runningPosition": [
          12,
          12,
          11,
          8
        ],
        "finishSeconds": 101.3,
        "winOdds": 15
      },
      {
        "placing": 9,
        "horseNo": 2,
        "horseId": "HK_2021_G306",
        "brandNo": "G306",
        "horseName": "KEEFY",
        "jockey": "K C Leung",
        "trainer": "F C Lor",
        "actualWeight": 133,
        "declaredHorseWeight": 1183,
        "draw": 9,
        "lbw": 5.5,
        "runningPosition": [
          6,
          6,
          3,
          9
        ],
        "finishSeconds": 101.46000000000001,
        "winOdds": 30
      },
      {
        "placing": 10,
        "horseNo": 4,
        "horseId": "HK_2022_H037",
        "brandNo": "H037",
        "horseName": "A AMERIC TE SPECSO",
        "jockey": "A Atzeni",
        "trainer": "J Size",
        "actualWeight": 129,
        "declaredHorseWeight": 1123,
        "draw": 7,
        "lbw": 6,
        "runningPosition": [
          9,
          9,
          10,
          10
        ],
        "finishSeconds": 101.53999999999999,
        "winOdds": 17
      },
      {
        "placing": 11,
        "horseNo": 5,
        "horseId": "HK_2024_K367",
        "brandNo": "K367",
        "horseName": "ANODE",
        "jockey": "D B McMonagle",
        "trainer": "C S Shum",
        "actualWeight": 124,
        "declaredHorseWeight": 1155,
        "draw": 10,
        "lbw": 6.75,
        "runningPosition": [
          4,
          4,
          5,
          11
        ],
        "finishSeconds": 101.66,
        "winOdds": 25
      },
      {
        "placing": 12,
        "horseNo": 12,
        "horseId": "HK_2021_G209",
        "brandNo": "G209",
        "horseName": "RISING FROM ASHES",
        "jockey": "H T Mo",
        "trainer": "C W Chang",
        "actualWeight": 113,
        "declaredHorseWeight": 1018,
        "draw": 2,
        "lbw": 10.75,
        "runningPosition": [
          7,
          7,
          9,
          12
        ],
        "finishSeconds": 102.31,
        "winOdds": 46
      }
    ],
    "dividends": {
      "win": [
        {
          "pool": "WIN",
          "combination": [
            6
          ],
          "dividendPer10": 17.5
        }
      ],
      "place": [
        {
          "pool": "PLACE",
          "combination": [
            6
          ],
          "dividendPer10": 11.5
        },
        {
          "pool": "PLACE",
          "combination": [
            3
          ],
          "dividendPer10": 14.5
        },
        {
          "pool": "PLACE",
          "combination": [
            9
          ],
          "dividendPer10": 74
        }
      ],
      "quinella": [
        {
          "pool": "QUINELLA",
          "combination": [
            3,
            6
          ],
          "dividendPer10": 39.5
        }
      ],
      "quinellaPlace": [
        {
          "pool": "QUINELLA PLACE",
          "combination": [
            3,
            6
          ],
          "dividendPer10": 21
        },
        {
          "pool": "QUINELLA PLACE",
          "combination": [
            6,
            9
          ],
          "dividendPer10": 85.5
        },
        {
          "pool": "QUINELLA PLACE",
          "combination": [
            3,
            9
          ],
          "dividendPer10": 139.5
        }
      ],
      "forecast": [
        {
          "pool": "FORECAST",
          "combination": [
            6,
            3
          ],
          "dividendPer10": 70
        }
      ],
      "tierce": [
        {
          "pool": "TIERCE",
          "combination": [
            6,
            3,
            9
          ],
          "dividendPer10": 821
        }
      ],
      "trio": [
        {
          "pool": "TRIO",
          "combination": [
            3,
            6,
            9
          ],
          "dividendPer10": 313
        }
      ],
      "first4": [
        {
          "pool": "FIRST 4",
          "combination": [
            3,
            6,
            7,
            9
          ],
          "dividendPer10": 2165
        }
      ],
      "quartet": [
        {
          "pool": "QUARTET",
          "combination": [
            6,
            3,
            9,
            7
          ],
          "dividendPer10": 19199
        }
      ]
    },
    "source": "https://racing.hkjc.com/en-us/local/information/localresults?racedate=2026%2F01%2F14&Racecourse=HV&RaceNo=5"
  },
  {
    "raceId": "2026-01-14-HV-6",
    "date": "2026-01-14",
    "racecourse": "HV",
    "raceNo": 6,
    "raceIndex": 350,
    "raceClass": 4,
    "distance": 1200,
    "ratingBand": "60-40",
    "surface": "TURF",
    "course": "TURF - \"B\" Course",
    "going": "GOOD",
    "runners": [
      {
        "placing": 1,
        "horseNo": 11,
        "horseId": "HK_2023_J116",
        "brandNo": "J116",
        "horseName": "WINNING MONEY",
        "jockey": "Z Purton",
        "trainer": "K W Lui",
        "actualWeight": 126,
        "declaredHorseWeight": 1194,
        "draw": 12,
        "lbw": 0,
        "runningPosition": [
          2,
          2,
          1
        ],
        "finishSeconds": 69.84,
        "winOdds": 4.4
      },
      {
        "placing": 2,
        "horseNo": 8,
        "horseId": "HK_2022_H317",
        "brandNo": "H317",
        "horseName": "DAN ATTACK",
        "jockey": "H Bowman",
        "trainer": "D J Whyte",
        "actualWeight": 126,
        "declaredHorseWeight": 1217,
        "draw": 8,
        "lbw": 0.05,
        "runningPosition": [
          10,
          10,
          2
        ],
        "finishSeconds": 69.88,
        "winOdds": 3.8
      },
      {
        "placing": 3,
        "horseNo": 9,
        "horseId": "HK_2023_J155",
        "brandNo": "J155",
        "horseName": "GREAT SPIRIT",
        "jockey": "A Atzeni",
        "trainer": "C H Yip",
        "actualWeight": 126,
        "declaredHorseWeight": 1097,
        "draw": 7,
        "lbw": 0.05,
        "runningPosition": [
          9,
          7,
          3
        ],
        "finishSeconds": 69.89,
        "winOdds": 8.4
      },
      {
        "placing": 4,
        "horseNo": 10,
        "horseId": "HK_2022_H057",
        "brandNo": "H057",
        "horseName": "SAME TO YOU",
        "jockey": "A Badel",
        "trainer": "M Newnham",
        "actualWeight": 126,
        "declaredHorseWeight": 992,
        "draw": 10,
        "lbw": 0.75,
        "runningPosition": [
          12,
          12,
          4
        ],
        "finishSeconds": 69.95,
        "winOdds": 33
      },
      {
        "placing": 5,
        "horseNo": 2,
        "horseId": "HK_2024_K125",
        "brandNo": "K125",
        "horseName": "SKY CAP",
        "jockey": "E C W Wong",
        "trainer": "C Fownes",
        "actualWeight": 128,
        "declaredHorseWeight": 1160,
        "draw": 9,
        "lbw": 0.75,
        "runningPosition": [
          1,
          1,
          5
        ],
        "finishSeconds": 69.98,
        "winOdds": 20
      },
      {
        "placing": 6,
        "horseNo": 7,
        "horseId": "HK_2023_J373",
        "brandNo": "J373",
        "horseName": "REWARDING BUDDY",
        "jockey": "K C Leung",
        "trainer": "F C Lor",
        "actualWeight": 127,
        "declaredHorseWeight": 1110,
        "draw": 3,
        "lbw": 1.5,
        "runningPosition": [
          6,
          6,
          6
        ],
        "finishSeconds": 70.08,
        "winOdds": 5.7
      },
      {
        "placing": 7,
        "horseNo": 1,
        "horseId": "HK_2024_K229",
        "brandNo": "K229",
        "horseName": "FREE PONY",
        "jockey": "J Orman",
        "trainer": "C W Chang",
        "actualWeight": 133,
        "declaredHorseWeight": 1161,
        "draw": 5,
        "lbw": 2.75,
        "runningPosition": [
          8,
          8,
          7
        ],
        "finishSeconds": 70.28,
        "winOdds": 14
      },
      {
        "placing": 8,
        "horseNo": 4,
        "horseId": "HK_2024_K570",
        "brandNo": "K570",
        "horseName": "PACKING KING",
        "jockey": "L Ferraris",
        "trainer": "P C Ng",
        "actualWeight": 129,
        "declaredHorseWeight": 1138,
        "draw": 1,
        "lbw": 3.75,
        "runningPosition": [
          4,
          4,
          8
        ],
        "finishSeconds": 70.43,
        "winOdds": 7.2
      },
      {
        "placing": 9,
        "horseNo": 12,
        "horseId": "HK_2023_J482",
        "brandNo": "J482",
        "horseName": "THOUSAND CUPS",
        "jockey": "Y L Chung",
        "trainer": "A S Cruz",
        "actualWeight": 116,
        "declaredHorseWeight": 1079,
        "draw": 11,
        "lbw": 5.25,
        "runningPosition": [
          3,
          3,
          9
        ],
        "finishSeconds": 70.67,
        "winOdds": 40
      },
      {
        "placing": 10,
        "horseNo": 3,
        "horseId": "HK_2024_K401",
        "brandNo": "K401",
        "horseName": "LEATHER GOODS",
        "jockey": "C L Chau",
        "trainer": "K L Man",
        "actualWeight": 127,
        "declaredHorseWeight": 1253,
        "draw": 4,
        "lbw": 7,
        "runningPosition": [
          7,
          9,
          10
        ],
        "finishSeconds": 70.95,
        "winOdds": 23
      },
      {
        "placing": 11,
        "horseNo": 5,
        "horseId": "HK_2024_K404",
        "brandNo": "K404",
        "horseName": "SKY PHOENIX",
        "jockey": "K Teetan",
        "trainer": "B Crawford",
        "actualWeight": 129,
        "declaredHorseWeight": 1164,
        "draw": 2,
        "lbw": 7.25,
        "runningPosition": [
          11,
          11,
          11
        ],
        "finishSeconds": 71,
        "winOdds": 39
      },
      {
        "placing": 12,
        "horseNo": 6,
        "horseId": "HK_2020_E435",
        "brandNo": "E435",
        "horseName": "AWESOME TREASURE",
        "jockey": "L Hewitson",
        "trainer": "D A Hayes",
        "actualWeight": 128,
        "declaredHorseWeight": 1172,
        "draw": 6,
        "lbw": 8.25,
        "runningPosition": [
          5,
          5,
          12
        ],
        "finishSeconds": 71.17,
        "winOdds": 20
      }
    ],
    "dividends": {
      "win": [
        {
          "pool": "WIN",
          "combination": [
            11
          ],
          "dividendPer10": 44
        }
      ],
      "place": [
        {
          "pool": "PLACE",
          "combination": [
            11
          ],
          "dividendPer10": 18.5
        },
        {
          "pool": "PLACE",
          "combination": [
            8
          ],
          "dividendPer10": 15.5
        },
        {
          "pool": "PLACE",
          "combination": [
            9
          ],
          "dividendPer10": 24
        }
      ],
      "quinella": [
        {
          "pool": "QUINELLA",
          "combination": [
            8,
            11
          ],
          "dividendPer10": 73.5
        }
      ],
      "quinellaPlace": [
        {
          "pool": "QUINELLA PLACE",
          "combination": [
            8,
            11
          ],
          "dividendPer10": 36
        },
        {
          "pool": "QUINELLA PLACE",
          "combination": [
            9,
            11
          ],
          "dividendPer10": 60.5
        },
        {
          "pool": "QUINELLA PLACE",
          "combination": [
            8,
            9
          ],
          "dividendPer10": 52
        }
      ],
      "forecast": [
        {
          "pool": "FORECAST",
          "combination": [
            11,
            8
          ],
          "dividendPer10": 194
        }
      ],
      "tierce": [
        {
          "pool": "TIERCE",
          "combination": [
            11,
            8,
            9
          ],
          "dividendPer10": 1211
        }
      ],
      "trio": [
        {
          "pool": "TRIO",
          "combination": [
            8,
            9,
            11
          ],
          "dividendPer10": 271
        }
      ],
      "first4": [
        {
          "pool": "FIRST 4",
          "combination": [
            8,
            9,
            10,
            11
          ],
          "dividendPer10": 915
        }
      ],
      "quartet": [
        {
          "pool": "QUARTET",
          "combination": [
            11,
            8,
            9,
            10
          ],
          "dividendPer10": 13321
        }
      ]
    },
    "source": "https://racing.hkjc.com/en-us/local/information/localresults?racedate=2026%2F01%2F14&Racecourse=HV&RaceNo=6"
  },
  {
    "raceId": "2026-01-14-HV-7",
    "date": "2026-01-14",
    "racecourse": "HV",
    "raceNo": 7,
    "raceIndex": 351,
    "raceClass": null,
    "distance": null,
    "ratingBand": null,
    "surface": "TURF",
    "course": "TURF - \"B\" Course",
    "going": "GOOD",
    "runners": [
      {
        "placing": 1,
        "horseNo": 8,
        "horseId": "HK_2022_H380",
        "brandNo": "H380",
        "horseName": "SPEED DRAGON",
        "jockey": "L Hewitson",
        "trainer": "K W Lui",
        "actualWeight": 117,
        "declaredHorseWeight": 1200,
        "draw": 7,
        "lbw": 0,
        "runningPosition": [
          9,
          8,
          10,
          12,
          1
        ],
        "finishSeconds": 108,
        "winOdds": 6.4
      },
      {
        "placing": 2,
        "horseNo": 10,
        "horseId": "HK_2023_J197",
        "brandNo": "J197",
        "horseName": "HUGE WAVE",
        "jockey": "A Badel",
        "trainer": "K H Ting",
        "actualWeight": 117,
        "declaredHorseWeight": 1217,
        "draw": 4,
        "lbw": 0.5,
        "runningPosition": [
          5,
          6,
          7,
          7,
          2
        ],
        "finishSeconds": 108.11,
        "winOdds": 5.3
      },
      {
        "placing": 3,
        "horseNo": 4,
        "horseId": "HK_2022_H215",
        "brandNo": "H215",
        "horseName": "HELENE FEELING",
        "jockey": "H Bowman",
        "trainer": "C S Shum",
        "actualWeight": 125,
        "declaredHorseWeight": 1251,
        "draw": 12,
        "lbw": 1.25,
        "runningPosition": [
          8,
          9,
          6,
          6,
          3
        ],
        "finishSeconds": 108.22,
        "winOdds": 5.3
      },
      {
        "placing": 4,
        "horseNo": 7,
        "horseId": "HK_2021_G236",
        "brandNo": "G236",
        "horseName": "ENCOUNTERED",
        "jockey": "K Teetan",
        "trainer": "B Crawford",
        "actualWeight": 123,
        "declaredHorseWeight": 1186,
        "draw": 5,
        "lbw": 1.5,
        "runningPosition": [
          4,
          4,
          4,
          4,
          4
        ],
        "finishSeconds": 108.22999999999999,
        "winOdds": 9.1
      },
      {
        "placing": 5,
        "horseNo": 12,
        "horseId": "HK_2024_K129",
        "brandNo": "K129",
        "horseName": "WINNING WING",
        "jockey": "H T Mo",
        "trainer": "K W Lui",
        "actualWeight": 115,
        "declaredHorseWeight": 1174,
        "draw": 6,
        "lbw": 2,
        "runningPosition": [
          12,
          11,
          3,
          3,
          5
        ],
        "finishSeconds": 108.34,
        "winOdds": 11
      },
      {
        "placing": 6,
        "horseNo": 6,
        "horseId": "HK_2023_J517",
        "brandNo": "J517",
        "horseName": "HONG LOK GOLF",
        "jockey": "H Bentley",
        "trainer": "W Y So",
        "actualWeight": 124,
        "declaredHorseWeight": 1149,
        "draw": 8,
        "lbw": 2.75,
        "runningPosition": [
          6,
          7,
          9,
          8,
          6
        ],
        "finishSeconds": 108.44,
        "winOdds": 6.2
      },
      {
        "placing": 7,
        "horseNo": 2,
        "horseId": "HK_2022_H212",
        "brandNo": "H212",
        "horseName": "CHANCHENG GLORY",
        "jockey": "M Guyon",
        "trainer": "K W Lui",
        "actualWeight": 131,
        "declaredHorseWeight": 1175,
        "draw": 1,
        "lbw": 2.75,
        "runningPosition": [
          2,
          3,
          5,
          5,
          7
        ],
        "finishSeconds": 108.45,
        "winOdds": 17
      },
      {
        "placing": 8,
        "horseNo": 1,
        "horseId": "HK_2020_E058",
        "brandNo": "E058",
        "horseName": "BEAUTY JOY",
        "jockey": "B Avdulla",
        "trainer": "A S Cruz",
        "actualWeight": 135,
        "declaredHorseWeight": 1061,
        "draw": 11,
        "lbw": 4.5,
        "runningPosition": [
          11,
          12,
          11,
          11,
          8
        ],
        "finishSeconds": 108.72,
        "winOdds": 25
      },
      {
        "placing": 9,
        "horseNo": 3,
        "horseId": "HK_2022_H474",
        "brandNo": "H474",
        "horseName": "MOMENTS IN TIME",
        "jockey": "Z Purton",
        "trainer": "C S Shum",
        "actualWeight": 128,
        "declaredHorseWeight": 1088,
        "draw": 9,
        "lbw": 5.75,
        "runningPosition": [
          10,
          10,
          12,
          10,
          9
        ],
        "finishSeconds": 108.91,
        "winOdds": 8.7
      },
      {
        "placing": 10,
        "horseNo": 5,
        "horseId": "HK_2022_H452",
        "brandNo": "H452",
        "horseName": "ENSUED",
        "jockey": "A Atzeni",
        "trainer": "J Size",
        "actualWeight": 124,
        "declaredHorseWeight": 1092,
        "draw": 3,
        "lbw": 6,
        "runningPosition": [
          7,
          5,
          8,
          9,
          10
        ],
        "finishSeconds": 108.97,
        "winOdds": 30
      },
      {
        "placing": 11,
        "horseNo": 11,
        "horseId": "HK_2023_J050",
        "brandNo": "J050",
        "horseName": "AWESOME FLUKE",
        "jockey": "M Chadwick",
        "trainer": "P F Yiu",
        "actualWeight": 115,
        "declaredHorseWeight": 1212,
        "draw": 2,
        "lbw": 6.75,
        "runningPosition": [
          3,
          2,
          2,
          2,
          11
        ],
        "finishSeconds": 109.09,
        "winOdds": 18
      },
      {
        "placing": 12,
        "horseNo": 9,
        "horseId": "HK_2022_H216",
        "brandNo": "H216",
        "horseName": "KAHOLO ANGEL",
        "jockey": "E C W Wong",
        "trainer": "C Fownes",
        "actualWeight": 115,
        "declaredHorseWeight": 1170,
        "draw": 10,
        "lbw": 10.25,
        "runningPosition": [
          1,
          1,
          1,
          1,
          12
        ],
        "finishSeconds": 109.65,
        "winOdds": 39
      }
    ],
    "dividends": {
      "win": [
        {
          "pool": "WIN",
          "combination": [
            8
          ],
          "dividendPer10": 64.5
        }
      ],
      "place": [
        {
          "pool": "PLACE",
          "combination": [
            8
          ],
          "dividendPer10": 23.5
        },
        {
          "pool": "PLACE",
          "combination": [
            10
          ],
          "dividendPer10": 20
        },
        {
          "pool": "PLACE",
          "combination": [
            4
          ],
          "dividendPer10": 20
        }
      ],
      "quinella": [
        {
          "pool": "QUINELLA",
          "combination": [
            8,
            10
          ],
          "dividendPer10": 166.5
        }
      ],
      "quinellaPlace": [
        {
          "pool": "QUINELLA PLACE",
          "combination": [
            8,
            10
          ],
          "dividendPer10": 60.5
        },
        {
          "pool": "QUINELLA PLACE",
          "combination": [
            4,
            8
          ],
          "dividendPer10": 74
        },
        {
          "pool": "QUINELLA PLACE",
          "combination": [
            4,
            10
          ],
          "dividendPer10": 55
        }
      ],
      "forecast": [
        {
          "pool": "FORECAST",
          "combination": [
            8,
            10
          ],
          "dividendPer10": 332
        }
      ],
      "tierce": [
        {
          "pool": "TIERCE",
          "combination": [
            8,
            10,
            4
          ],
          "dividendPer10": 2172
        }
      ],
      "trio": [
        {
          "pool": "TRIO",
          "combination": [
            4,
            8,
            10
          ],
          "dividendPer10": 323
        }
      ],
      "first4": [
        {
          "pool": "FIRST 4",
          "combination": [
            4,
            7,
            8,
            10
          ],
          "dividendPer10": 866
        }
      ],
      "quartet": [
        {
          "pool": "QUARTET",
          "combination": [
            8,
            10,
            4,
            7
          ],
          "dividendPer10": 16613
        }
      ]
    },
    "source": "https://racing.hkjc.com/en-us/local/information/localresults?racedate=2026%2F01%2F14&Racecourse=HV&RaceNo=7"
  },
  {
    "raceId": "2026-01-14-HV-8",
    "date": "2026-01-14",
    "racecourse": "HV",
    "raceNo": 8,
    "raceIndex": 352,
    "raceClass": 2,
    "distance": 1200,
    "ratingBand": "100-80",
    "surface": "TURF",
    "course": "TURF - \"B\" Course",
    "going": "GOOD",
    "runners": [
      {
        "placing": 1,
        "horseNo": 2,
        "horseId": "HK_2023_J027",
        "brandNo": "J027",
        "horseName": "STORM RIDER",
        "jockey": "H Bowman",
        "trainer": "D A Hayes",
        "actualWeight": 132,
        "declaredHorseWeight": 1151,
        "draw": 1,
        "lbw": 0,
        "runningPosition": [
          5,
          4,
          1
        ],
        "finishSeconds": 69.27,
        "winOdds": 4.2
      },
      {
        "placing": 2,
        "horseNo": 11,
        "horseId": "HK_2024_K258",
        "brandNo": "K258",
        "horseName": "REGAL GEM",
        "jockey": "K C Leung",
        "trainer": "F C Lor",
        "actualWeight": 119,
        "declaredHorseWeight": 1125,
        "draw": 8,
        "lbw": 1,
        "runningPosition": [
          9,
          9,
          2
        ],
        "finishSeconds": 69.44,
        "winOdds": 5.4
      },
      {
        "placing": 3,
        "horseNo": 6,
        "horseId": "HK_2021_G268",
        "brandNo": "G268",
        "horseName": "BRAVE STAR",
        "jockey": "C Y Ho",
        "trainer": "K W Lui",
        "actualWeight": 121,
        "declaredHorseWeight": 1111,
        "draw": 5,
        "lbw": 1.25,
        "runningPosition": [
          8,
          8,
          3
        ],
        "finishSeconds": 69.49,
        "winOdds": 23
      },
      {
        "placing": 4,
        "horseNo": 12,
        "horseId": "HK_2023_J303",
        "brandNo": "J303",
        "horseName": "GUSTOSISIMO",
        "jockey": "M Guyon",
        "trainer": "A S Cruz",
        "actualWeight": 118,
        "declaredHorseWeight": 1197,
        "draw": 2,
        "lbw": 1.75,
        "runningPosition": [
          6,
          7,
          4
        ],
        "finishSeconds": 69.53999999999999,
        "winOdds": 3.8
      },
      {
        "placing": 5,
        "horseNo": 10,
        "horseId": "HK_2023_J325",
        "brandNo": "J325",
        "horseName": "MASTEROFMYUNIVERSE",
        "jockey": "K Teetan",
        "trainer": "J Size",
        "actualWeight": 119,
        "declaredHorseWeight": 985,
        "draw": 7,
        "lbw": 2,
        "runningPosition": [
          11,
          11,
          5
        ],
        "finishSeconds": 69.6,
        "winOdds": 12
      },
      {
        "placing": 6,
        "horseNo": 3,
        "horseId": "HK_2021_G265",
        "brandNo": "G265",
        "horseName": "SON PAK FU",
        "jockey": "M Chadwick",
        "trainer": "A S Cruz",
        "actualWeight": 124,
        "declaredHorseWeight": 1183,
        "draw": 9,
        "lbw": 2.25,
        "runningPosition": [
          12,
          12,
          6
        ],
        "finishSeconds": 69.64,
        "winOdds": 21
      },
      {
        "placing": 7,
        "horseNo": 7,
        "horseId": "HK_2024_K173",
        "brandNo": "K173",
        "horseName": "CRIMSON FLASH",
        "jockey": "A Atzeni",
        "trainer": "M Newnham",
        "actualWeight": 121,
        "declaredHorseWeight": 1088,
        "draw": 12,
        "lbw": 3,
        "runningPosition": [
          10,
          10,
          7
        ],
        "finishSeconds": 69.73,
        "winOdds": 5.5
      },
      {
        "placing": 8,
        "horseNo": 5,
        "horseId": "HK_2023_J082",
        "brandNo": "J082",
        "horseName": "YOUTHFUL SPIRITS",
        "jockey": "L Ferraris",
        "trainer": "M Newnham",
        "actualWeight": 122,
        "declaredHorseWeight": 1068,
        "draw": 10,
        "lbw": 3,
        "runningPosition": [
          1,
          1,
          8
        ],
        "finishSeconds": 69.76,
        "winOdds": 27
      },
      {
        "placing": 9,
        "horseNo": 4,
        "horseId": "HK_2022_H092",
        "brandNo": "H092",
        "horseName": "SUPERB CAPITALIST",
        "jockey": "Y L Chung",
        "trainer": "A S Cruz",
        "actualWeight": 120,
        "declaredHorseWeight": 1159,
        "draw": 3,
        "lbw": 3.5,
        "runningPosition": [
          3,
          2,
          9
        ],
        "finishSeconds": 69.81,
        "winOdds": 26
      },
      {
        "placing": 10,
        "horseNo": 1,
        "horseId": "HK_2023_J333",
        "brandNo": "J333",
        "horseName": "MAGIC CONTROL",
        "jockey": "C L Chau",
        "trainer": "W K Mo",
        "actualWeight": 133,
        "declaredHorseWeight": 1094,
        "draw": 6,
        "lbw": 4.75,
        "runningPosition": [
          7,
          6,
          10
        ],
        "finishSeconds": 70.01,
        "winOdds": 16
      },
      {
        "placing": 11,
        "horseNo": 9,
        "horseId": "HK_2020_E061",
        "brandNo": "E061",
        "horseName": "HARMONY N BLESSED",
        "jockey": "L Hewitson",
        "trainer": "D A Hayes",
        "actualWeight": 119,
        "declaredHorseWeight": 1218,
        "draw": 11,
        "lbw": 4.75,
        "runningPosition": [
          4,
          5,
          11
        ],
        "finishSeconds": 70.02,
        "winOdds": 53
      },
      {
        "placing": 12,
        "horseNo": 8,
        "horseId": "HK_2022_H246",
        "brandNo": "H246",
        "horseName": "PACKING BOLE",
        "jockey": "H T Mo",
        "trainer": "C S Shum",
        "actualWeight": 118,
        "declaredHorseWeight": 1253,
        "draw": 4,
        "lbw": 22.5,
        "runningPosition": [
          2,
          3,
          12
        ],
        "finishSeconds": 72.88,
        "winOdds": 45
      }
    ],
    "dividends": {
      "win": [
        {
          "pool": "WIN",
          "combination": [
            2
          ],
          "dividendPer10": 42
        }
      ],
      "place": [
        {
          "pool": "PLACE",
          "combination": [
            2
          ],
          "dividendPer10": 17
        },
        {
          "pool": "PLACE",
          "combination": [
            11
          ],
          "dividendPer10": 17.5
        },
        {
          "pool": "PLACE",
          "combination": [
            6
          ],
          "dividendPer10": 64
        }
      ],
      "quinella": [
        {
          "pool": "QUINELLA",
          "combination": [
            2,
            11
          ],
          "dividendPer10": 135
        }
      ],
      "quinellaPlace": [
        {
          "pool": "QUINELLA PLACE",
          "combination": [
            2,
            11
          ],
          "dividendPer10": 47
        },
        {
          "pool": "QUINELLA PLACE",
          "combination": [
            2,
            6
          ],
          "dividendPer10": 170.5
        },
        {
          "pool": "QUINELLA PLACE",
          "combination": [
            6,
            11
          ],
          "dividendPer10": 184
        }
      ],
      "forecast": [
        {
          "pool": "FORECAST",
          "combination": [
            2,
            11
          ],
          "dividendPer10": 254
        }
      ],
      "tierce": [
        {
          "pool": "TIERCE",
          "combination": [
            2,
            11,
            6
          ],
          "dividendPer10": 3130
        }
      ],
      "trio": [
        {
          "pool": "TRIO",
          "combination": [
            2,
            6,
            11
          ],
          "dividendPer10": 333
        }
      ],
      "first4": [
        {
          "pool": "FIRST 4",
          "combination": [
            2,
            6,
            11,
            12
          ],
          "dividendPer10": 591
        }
      ],
      "quartet": [
        {
          "pool": "QUARTET",
          "combination": [
            2,
            11,
            6,
            12
          ],
          "dividendPer10": 14635
        }
      ]
    },
    "source": "https://racing.hkjc.com/en-us/local/information/localresults?racedate=2026%2F01%2F14&Racecourse=HV&RaceNo=8"
  },
  {
    "raceId": "2026-01-14-HV-9",
    "date": "2026-01-14",
    "racecourse": "HV",
    "raceNo": 9,
    "raceIndex": 353,
    "raceClass": 3,
    "distance": 1200,
    "ratingBand": "80-60",
    "surface": "TURF",
    "course": "TURF - \"B\" Course",
    "going": "GOOD",
    "runners": [
      {
        "placing": 1,
        "horseNo": 11,
        "horseId": "HK_2023_J360",
        "brandNo": "J360",
        "horseName": "MIGHTY COMMANDER",
        "jockey": "A Badel",
        "trainer": "C Fownes",
        "actualWeight": 120,
        "declaredHorseWeight": 1078,
        "draw": 9,
        "lbw": 0,
        "runningPosition": [
          12,
          12,
          1
        ],
        "finishSeconds": 69.44,
        "winOdds": 7.4
      },
      {
        "placing": 2,
        "horseNo": 6,
        "horseId": "HK_2024_K238",
        "brandNo": "K238",
        "horseName": "PERFECTDAY",
        "jockey": "Z Purton",
        "trainer": "W Y So",
        "actualWeight": 123,
        "declaredHorseWeight": 1087,
        "draw": 5,
        "lbw": 1,
        "runningPosition": [
          7,
          8,
          2
        ],
        "finishSeconds": 69.59,
        "winOdds": 4.8
      },
      {
        "placing": 3,
        "horseNo": 12,
        "horseId": "HK_2023_J370",
        "brandNo": "J370",
        "horseName": "CALIFORNIA BLITZ",
        "jockey": "M Chadwick",
        "trainer": "W K Mo",
        "actualWeight": 118,
        "declaredHorseWeight": 1084,
        "draw": 3,
        "lbw": 1.25,
        "runningPosition": [
          3,
          5,
          3
        ],
        "finishSeconds": 69.61,
        "winOdds": 7
      },
      {
        "placing": 4,
        "horseNo": 9,
        "horseId": "HK_2024_K202",
        "brandNo": "K202",
        "horseName": "FRIENDS OF SHAJING",
        "jockey": "C L Chau",
        "trainer": "C S Shum",
        "actualWeight": 121,
        "declaredHorseWeight": 1113,
        "draw": 4,
        "lbw": 2.25,
        "runningPosition": [
          4,
          6,
          4
        ],
        "finishSeconds": 69.82,
        "winOdds": 5.6
      },
      {
        "placing": 5,
        "horseNo": 5,
        "horseId": "HK_2022_H456",
        "brandNo": "H456",
        "horseName": "SPORTS LEGEND",
        "jockey": "Y L Chung",
        "trainer": "D Eustace",
        "actualWeight": 126,
        "declaredHorseWeight": 1172,
        "draw": 1,
        "lbw": 2.5,
        "runningPosition": [
          6,
          7,
          5
        ],
        "finishSeconds": 69.84,
        "winOdds": 3
      },
      {
        "placing": 6,
        "horseNo": 3,
        "horseId": "HK_2024_K352",
        "brandNo": "K352",
        "horseName": "SYMBOL OF STRENGTH",
        "jockey": "L Ferraris",
        "trainer": "F C Lor",
        "actualWeight": 130,
        "declaredHorseWeight": 1146,
        "draw": 8,
        "lbw": 2.5,
        "runningPosition": [
          2,
          3,
          6
        ],
        "finishSeconds": 69.85,
        "winOdds": 40
      },
      {
        "placing": 7,
        "horseNo": 4,
        "horseId": "HK_2020_E301",
        "brandNo": "E301",
        "horseName": "POWER KOEPP",
        "jockey": "H Bowman",
        "trainer": "M Newnham",
        "actualWeight": 129,
        "declaredHorseWeight": 1111,
        "draw": 11,
        "lbw": 3,
        "runningPosition": [
          5,
          2,
          7
        ],
        "finishSeconds": 69.94,
        "winOdds": 14
      },
      {
        "placing": 8,
        "horseNo": 2,
        "horseId": "HK_2023_J158",
        "brandNo": "J158",
        "horseName": "KING MILES",
        "jockey": "C Y Ho",
        "trainer": "K W Lui",
        "actualWeight": 133,
        "declaredHorseWeight": 1159,
        "draw": 12,
        "lbw": 3.25,
        "runningPosition": [
          8,
          4,
          8
        ],
        "finishSeconds": 69.97,
        "winOdds": 26
      },
      {
        "placing": 9,
        "horseNo": 1,
        "horseId": "HK_2021_G455",
        "brandNo": "G455",
        "horseName": "WONDER KIT",
        "jockey": "L Hewitson",
        "trainer": "Y S Tsui",
        "actualWeight": 135,
        "declaredHorseWeight": 1118,
        "draw": 10,
        "lbw": 4,
        "runningPosition": [
          1,
          1,
          9
        ],
        "finishSeconds": 70.07,
        "winOdds": 53
      },
      {
        "placing": 10,
        "horseNo": 7,
        "horseId": "HK_2021_G016",
        "brandNo": "G016",
        "horseName": "SUGAR SUGAR",
        "jockey": "D Probert",
        "trainer": "C Fownes",
        "actualWeight": 122,
        "declaredHorseWeight": 1097,
        "draw": 6,
        "lbw": 4,
        "runningPosition": [
          10,
          9,
          10
        ],
        "finishSeconds": 70.08,
        "winOdds": 29
      },
      {
        "placing": 11,
        "horseNo": 8,
        "horseId": "HK_2025_L055",
        "brandNo": "L055",
        "horseName": "ALWAYS AHEAD",
        "jockey": "M F Poon",
        "trainer": "K L Man",
        "actualWeight": 121,
        "declaredHorseWeight": 1184,
        "draw": 2,
        "lbw": 4.75,
        "runningPosition": [
          9,
          10,
          11
        ],
        "finishSeconds": 70.2,
        "winOdds": 58
      },
      {
        "placing": 12,
        "horseNo": 10,
        "horseId": "HK_2025_L120",
        "brandNo": "L120",
        "horseName": "RYUI KOKOROE",
        "jockey": "H Bentley",
        "trainer": "D A Hayes",
        "actualWeight": 121,
        "declaredHorseWeight": 1117,
        "draw": 7,
        "lbw": 5.25,
        "runningPosition": [
          11,
          11,
          12
        ],
        "finishSeconds": 70.28,
        "winOdds": 73
      }
    ],
    "dividends": {
      "win": [
        {
          "pool": "WIN",
          "combination": [
            11
          ],
          "dividendPer10": 74
        }
      ],
      "place": [
        {
          "pool": "PLACE",
          "combination": [
            11
          ],
          "dividendPer10": 23.5
        },
        {
          "pool": "PLACE",
          "combination": [
            6
          ],
          "dividendPer10": 19
        },
        {
          "pool": "PLACE",
          "combination": [
            12
          ],
          "dividendPer10": 21.5
        }
      ],
      "quinella": [
        {
          "pool": "QUINELLA",
          "combination": [
            6,
            11
          ],
          "dividendPer10": 238
        }
      ],
      "quinellaPlace": [
        {
          "pool": "QUINELLA PLACE",
          "combination": [
            6,
            11
          ],
          "dividendPer10": 77
        },
        {
          "pool": "QUINELLA PLACE",
          "combination": [
            11,
            12
          ],
          "dividendPer10": 79
        },
        {
          "pool": "QUINELLA PLACE",
          "combination": [
            6,
            12
          ],
          "dividendPer10": 58
        }
      ],
      "forecast": [
        {
          "pool": "FORECAST",
          "combination": [
            11,
            6
          ],
          "dividendPer10": 436
        }
      ],
      "tierce": [
        {
          "pool": "TIERCE",
          "combination": [
            11,
            6,
            12
          ],
          "dividendPer10": 2734
        }
      ],
      "trio": [
        {
          "pool": "TRIO",
          "combination": [
            6,
            11,
            12
          ],
          "dividendPer10": 418
        }
      ],
      "first4": [
        {
          "pool": "FIRST 4",
          "combination": [
            6,
            9,
            11,
            12
          ],
          "dividendPer10": 381
        }
      ],
      "quartet": [
        {
          "pool": "QUARTET",
          "combination": [
            11,
            6,
            12,
            9
          ],
          "dividendPer10": 13975
        }
      ]
    },
    "source": "https://racing.hkjc.com/en-us/local/information/localresults?racedate=2026%2F01%2F14&Racecourse=HV&RaceNo=9"
  }
]
